{
"meta":{"test_sets":[],"test_metrics":[],"learn_metrics":[{"best_value":"Min","name":"RMSE"}],"launch_mode":"Train","parameters":"","iteration_count":1000,"learn_sets":["learn"],"name":"experiment"},
"iterations":[
{"learn":[21785.57311],"iteration":0,"passed_time":0.04195949516,"remaining_time":41.91753567},
{"learn":[21023.6698],"iteration":1,"passed_time":0.07280534409,"remaining_time":36.3298667},
{"learn":[20366.81105],"iteration":2,"passed_time":0.1160405132,"remaining_time":38.56413055},
{"learn":[19796.63046],"iteration":3,"passed_time":0.1593364052,"remaining_time":39.6747649},
{"learn":[19330.94154],"iteration":4,"passed_time":0.1920295557,"remaining_time":38.21388159},
{"learn":[18913.21429],"iteration":5,"passed_time":0.2284641912,"remaining_time":37.848901},
{"learn":[18568.81809],"iteration":6,"passed_time":0.2614838293,"remaining_time":37.09334892},
{"learn":[18265.73046],"iteration":7,"passed_time":0.2904042561,"remaining_time":36.01012775},
{"learn":[18006.19191],"iteration":8,"passed_time":0.3297593562,"remaining_time":36.31016911},
{"learn":[17416.45016],"iteration":9,"passed_time":0.3751656994,"remaining_time":37.14140424},
{"learn":[17145.56077],"iteration":10,"passed_time":0.420876769,"remaining_time":37.84064768},
{"learn":[16913.45951],"iteration":11,"passed_time":0.4700418736,"remaining_time":38.70011426},
{"learn":[16408.64006],"iteration":12,"passed_time":0.5201578241,"remaining_time":39.49198249},
{"learn":[16194.18438],"iteration":13,"passed_time":0.5533787052,"remaining_time":38.97367166},
{"learn":[16017.41091],"iteration":14,"passed_time":0.594166821,"remaining_time":39.01695458},
{"learn":[15593.63101],"iteration":15,"passed_time":0.6421947896,"remaining_time":39.49497956},
{"learn":[15436.71265],"iteration":16,"passed_time":0.6847309712,"remaining_time":39.59356145},
{"learn":[15083.92069],"iteration":17,"passed_time":0.7213770922,"remaining_time":39.35512803},
{"learn":[14954.35556],"iteration":18,"passed_time":0.7635491096,"remaining_time":39.42324613},
{"learn":[14828.07309],"iteration":19,"passed_time":0.7977168955,"remaining_time":39.08812788},
{"learn":[14683.31342],"iteration":20,"passed_time":0.8344599839,"remaining_time":38.90172973},
{"learn":[14574.29515],"iteration":21,"passed_time":0.8730686669,"remaining_time":38.81187074},
{"learn":[14455.1016],"iteration":22,"passed_time":0.9070746683,"remaining_time":38.53095439},
{"learn":[14231.85],"iteration":23,"passed_time":0.9507188232,"remaining_time":38.66256548},
{"learn":[14164.23797],"iteration":24,"passed_time":0.9940815274,"remaining_time":38.76917957},
{"learn":[13937.93249],"iteration":25,"passed_time":1.037388714,"remaining_time":38.8621772},
{"learn":[13842.18191],"iteration":26,"passed_time":1.078687014,"remaining_time":38.87268388},
{"learn":[13651.64318],"iteration":27,"passed_time":1.123946126,"remaining_time":39.01698695},
{"learn":[13570.0423],"iteration":28,"passed_time":1.171937003,"remaining_time":39.23968379},
{"learn":[13408.02449],"iteration":29,"passed_time":1.213385951,"remaining_time":39.23281242},
{"learn":[13325.66096],"iteration":30,"passed_time":1.254930301,"remaining_time":39.22669231},
{"learn":[13254.91687],"iteration":31,"passed_time":1.296931284,"remaining_time":39.23217133},
{"learn":[13175.20495],"iteration":32,"passed_time":1.336052187,"remaining_time":39.15037773},
{"learn":[13097.84015],"iteration":33,"passed_time":1.370957238,"remaining_time":38.95131448},
{"learn":[13039.11359],"iteration":34,"passed_time":1.416763737,"remaining_time":39.06220018},
{"learn":[12912.8584],"iteration":35,"passed_time":1.459850357,"remaining_time":39.09154844},
{"learn":[12857.02267],"iteration":36,"passed_time":1.504117643,"remaining_time":39.14771055},
{"learn":[12767.11854],"iteration":37,"passed_time":1.550986783,"remaining_time":39.26445487},
{"learn":[12695.64781],"iteration":38,"passed_time":1.594638065,"remaining_time":39.29351746},
{"learn":[12658.82809],"iteration":39,"passed_time":1.637411206,"remaining_time":39.29786893},
{"learn":[12547.29086],"iteration":40,"passed_time":1.677317659,"remaining_time":39.23286915},
{"learn":[12456.39734],"iteration":41,"passed_time":1.722303079,"remaining_time":39.28491308},
{"learn":[12403.83902],"iteration":42,"passed_time":1.76738306,"remaining_time":39.33454858},
{"learn":[12359.23324],"iteration":43,"passed_time":1.806113992,"remaining_time":39.24193129},
{"learn":[12295.53905],"iteration":44,"passed_time":1.84347452,"remaining_time":39.12262592},
{"learn":[12255.42527],"iteration":45,"passed_time":1.902162924,"remaining_time":39.44920499},
{"learn":[12198.49683],"iteration":46,"passed_time":1.957067841,"remaining_time":39.68267346},
{"learn":[12148.83526],"iteration":47,"passed_time":2.005657214,"remaining_time":39.77886808},
{"learn":[12050.03762],"iteration":48,"passed_time":2.049920918,"remaining_time":39.78519986},
{"learn":[12020.52018],"iteration":49,"passed_time":2.090189301,"remaining_time":39.71359673},
{"learn":[11942.66968],"iteration":50,"passed_time":2.131075861,"remaining_time":39.65472533},
{"learn":[11896.40292],"iteration":51,"passed_time":2.176150888,"remaining_time":39.67290465},
{"learn":[11866.22131],"iteration":52,"passed_time":2.214302871,"remaining_time":39.56499659},
{"learn":[11808.18428],"iteration":53,"passed_time":2.255390985,"remaining_time":39.51110874},
{"learn":[11743.07158],"iteration":54,"passed_time":2.308061098,"remaining_time":39.65668614},
{"learn":[11709.27049],"iteration":55,"passed_time":2.34708754,"remaining_time":39.56518996},
{"learn":[11664.50225],"iteration":56,"passed_time":2.386729332,"remaining_time":39.48571509},
{"learn":[11609.90991],"iteration":57,"passed_time":2.424172787,"remaining_time":39.37190975},
{"learn":[11574.33912],"iteration":58,"passed_time":2.461016302,"remaining_time":39.25112441},
{"learn":[11531.36794],"iteration":59,"passed_time":2.499422184,"remaining_time":39.15761421},
{"learn":[11504.65805],"iteration":60,"passed_time":2.54209168,"remaining_time":39.13154242},
{"learn":[11441.02187],"iteration":61,"passed_time":2.579670755,"remaining_time":39.02792207},
{"learn":[11399.94615],"iteration":62,"passed_time":2.617338499,"remaining_time":38.92771704},
{"learn":[11371.68202],"iteration":63,"passed_time":2.65015237,"remaining_time":38.75847842},
{"learn":[11322.52997],"iteration":64,"passed_time":2.688431346,"remaining_time":38.6720509},
{"learn":[11270.44877],"iteration":65,"passed_time":2.730962165,"remaining_time":38.64725246},
{"learn":[11235.09144],"iteration":66,"passed_time":2.768733666,"remaining_time":38.55564941},
{"learn":[11209.58993],"iteration":67,"passed_time":2.810453472,"remaining_time":38.51974464},
{"learn":[11181.63889],"iteration":68,"passed_time":2.848358593,"remaining_time":38.43220073},
{"learn":[11158.04005],"iteration":69,"passed_time":2.891421368,"remaining_time":38.41459817},
{"learn":[11122.38104],"iteration":70,"passed_time":2.929575536,"remaining_time":38.33205173},
{"learn":[11102.26177],"iteration":71,"passed_time":2.970978191,"remaining_time":38.2926078},
{"learn":[11068.09273],"iteration":72,"passed_time":3.011780263,"remaining_time":38.24548362},
{"learn":[11036.48622],"iteration":73,"passed_time":3.051493182,"remaining_time":38.18490117},
{"learn":[10993.47073],"iteration":74,"passed_time":3.093460611,"remaining_time":38.15268087},
{"learn":[10965.1618],"iteration":75,"passed_time":3.129520402,"remaining_time":38.04837963},
{"learn":[10915.18389],"iteration":76,"passed_time":3.170359044,"remaining_time":38.00313504},
{"learn":[10893.43641],"iteration":77,"passed_time":3.211779662,"remaining_time":37.96488267},
{"learn":[10874.79068],"iteration":78,"passed_time":3.253575496,"remaining_time":37.93092445},
{"learn":[10854.6015],"iteration":79,"passed_time":3.296567587,"remaining_time":37.91052725},
{"learn":[10819.25992],"iteration":80,"passed_time":3.334468259,"remaining_time":37.83180654},
{"learn":[10789.37361],"iteration":81,"passed_time":3.375266442,"remaining_time":37.78651943},
{"learn":[10715.63907],"iteration":82,"passed_time":3.414437319,"remaining_time":37.72336171},
{"learn":[10694.1166],"iteration":83,"passed_time":3.450728269,"remaining_time":37.62937017},
{"learn":[10675.21189],"iteration":84,"passed_time":3.492655963,"remaining_time":37.59741419},
{"learn":[10647.70018],"iteration":85,"passed_time":3.533322219,"remaining_time":37.55181987},
{"learn":[10584.30393],"iteration":86,"passed_time":3.565502103,"remaining_time":37.41728069},
{"learn":[10557.31535],"iteration":87,"passed_time":3.595582769,"remaining_time":37.26331233},
{"learn":[10504.99783],"iteration":88,"passed_time":3.635379271,"remaining_time":37.21157883},
{"learn":[10451.17173],"iteration":89,"passed_time":3.658689209,"remaining_time":36.99341312},
{"learn":[10418.46182],"iteration":90,"passed_time":3.697052476,"remaining_time":36.92989781},
{"learn":[10382.82377],"iteration":91,"passed_time":3.733881081,"remaining_time":36.85178284},
{"learn":[10337.36188],"iteration":92,"passed_time":3.772916292,"remaining_time":36.79607609},
{"learn":[10318.97127],"iteration":93,"passed_time":3.819500955,"remaining_time":36.81348793},
{"learn":[10288.44258],"iteration":94,"passed_time":3.862954058,"remaining_time":36.79972023},
{"learn":[10257.77463],"iteration":95,"passed_time":3.901566591,"remaining_time":36.73975207},
{"learn":[10211.83039],"iteration":96,"passed_time":3.947205071,"remaining_time":36.74563071},
{"learn":[10183.83056],"iteration":97,"passed_time":3.990310116,"remaining_time":36.72714005},
{"learn":[10165.05801],"iteration":98,"passed_time":4.032920254,"remaining_time":36.70364796},
{"learn":[10148.57892],"iteration":99,"passed_time":4.07350968,"remaining_time":36.66158712},
{"learn":[10121.47716],"iteration":100,"passed_time":4.113537778,"remaining_time":36.61455904},
{"learn":[10053.70375],"iteration":101,"passed_time":4.156497456,"remaining_time":36.5934776},
{"learn":[10036.40961],"iteration":102,"passed_time":4.197749254,"remaining_time":36.55709787},
{"learn":[10002.60505],"iteration":103,"passed_time":4.239738764,"remaining_time":36.52698012},
{"learn":[9976.920703],"iteration":104,"passed_time":4.277693041,"remaining_time":36.46224068},
{"learn":[9934.565587],"iteration":105,"passed_time":4.315409425,"remaining_time":36.39600024},
{"learn":[9909.828654],"iteration":106,"passed_time":4.355940191,"remaining_time":36.35378122},
{"learn":[9876.442094],"iteration":107,"passed_time":4.395086343,"remaining_time":36.30015757},
{"learn":[9854.158206],"iteration":108,"passed_time":4.436214871,"remaining_time":36.26300413},
{"learn":[9836.654094],"iteration":109,"passed_time":4.478590224,"remaining_time":36.23586636},
{"learn":[9816.207326],"iteration":110,"passed_time":4.521363795,"remaining_time":36.21164337},
{"learn":[9779.877872],"iteration":111,"passed_time":4.561391893,"remaining_time":36.16532144},
{"learn":[9752.299712],"iteration":112,"passed_time":4.600119758,"remaining_time":36.10890465},
{"learn":[9720.117089],"iteration":113,"passed_time":4.63592552,"remaining_time":36.03008782},
{"learn":[9698.040119],"iteration":114,"passed_time":4.674226571,"remaining_time":35.97122187},
{"learn":[9685.119407],"iteration":115,"passed_time":4.715894003,"remaining_time":35.93836464},
{"learn":[9663.021072],"iteration":116,"passed_time":4.756323722,"remaining_time":35.89601579},
{"learn":[9638.042102],"iteration":117,"passed_time":4.796174576,"remaining_time":35.84937268},
{"learn":[9621.496506],"iteration":118,"passed_time":4.830702684,"remaining_time":35.76343752},
{"learn":[9601.228129],"iteration":119,"passed_time":4.866830723,"remaining_time":35.69009197},
{"learn":[9588.282865],"iteration":120,"passed_time":4.911831214,"remaining_time":35.68181518},
{"learn":[9563.394539],"iteration":121,"passed_time":4.958995787,"remaining_time":35.68851066},
{"learn":[9541.367669],"iteration":122,"passed_time":5.000249409,"remaining_time":35.65218481},
{"learn":[9522.100875],"iteration":123,"passed_time":5.041404526,"remaining_time":35.61508359},
{"learn":[9506.081709],"iteration":124,"passed_time":5.084821115,"remaining_time":35.5937478},
{"learn":[9489.380641],"iteration":125,"passed_time":5.130929008,"remaining_time":35.59072979},
{"learn":[9476.798462],"iteration":126,"passed_time":5.171869662,"remaining_time":35.5515135},
{"learn":[9456.546647],"iteration":127,"passed_time":5.203919815,"remaining_time":35.45170374},
{"learn":[9440.48897],"iteration":128,"passed_time":5.250343164,"remaining_time":35.44999144},
{"learn":[9419.142871],"iteration":129,"passed_time":5.290591447,"remaining_time":35.40626584},
{"learn":[9386.116797],"iteration":130,"passed_time":5.335048435,"remaining_time":35.39051214},
{"learn":[9374.014466],"iteration":131,"passed_time":5.37581403,"remaining_time":35.35004984},
{"learn":[9360.887404],"iteration":132,"passed_time":5.414921215,"remaining_time":35.29877213},
{"learn":[9353.976749],"iteration":133,"passed_time":5.456423205,"remaining_time":35.26315295},
{"learn":[9336.899609],"iteration":134,"passed_time":5.49815435,"remaining_time":35.22891491},
{"learn":[9319.560551],"iteration":135,"passed_time":5.54239774,"remaining_time":35.21052682},
{"learn":[9301.721368],"iteration":136,"passed_time":5.580761413,"remaining_time":35.15472335},
{"learn":[9290.389049],"iteration":137,"passed_time":5.621715477,"remaining_time":35.1153532},
{"learn":[9266.083369],"iteration":138,"passed_time":5.665344526,"remaining_time":35.09252976},
{"learn":[9250.206022],"iteration":139,"passed_time":5.708117236,"remaining_time":35.06414874},
{"learn":[9233.061819],"iteration":140,"passed_time":5.748206004,"remaining_time":35.01921246},
{"learn":[9213.484032],"iteration":141,"passed_time":5.787712002,"remaining_time":34.97082322},
{"learn":[9194.551326],"iteration":142,"passed_time":5.829794436,"remaining_time":34.93799882},
{"learn":[9180.257146],"iteration":143,"passed_time":5.872177804,"remaining_time":34.90683472},
{"learn":[9164.473205],"iteration":144,"passed_time":5.915892014,"remaining_time":34.88336325},
{"learn":[9128.404923],"iteration":145,"passed_time":5.958432328,"remaining_time":34.852748},
{"learn":[9114.677088],"iteration":146,"passed_time":6.000862465,"remaining_time":34.82133117},
{"learn":[9092.034254],"iteration":147,"passed_time":6.035621402,"remaining_time":34.74560429},
{"learn":[9077.06628],"iteration":148,"passed_time":6.075031265,"remaining_time":34.69699065},
{"learn":[9062.805198],"iteration":149,"passed_time":6.119581229,"remaining_time":34.67762697},
{"learn":[9054.702925],"iteration":150,"passed_time":6.164061979,"remaining_time":34.65754053},
{"learn":[9043.746186],"iteration":151,"passed_time":6.210770369,"remaining_time":34.64956101},
{"learn":[9022.337024],"iteration":152,"passed_time":6.253969124,"remaining_time":34.62164607},
{"learn":[9010.505148],"iteration":153,"passed_time":6.297125389,"remaining_time":34.59329921},
{"learn":[8990.687366],"iteration":154,"passed_time":6.340799679,"remaining_time":34.56758534},
{"learn":[8973.583407],"iteration":155,"passed_time":6.386354317,"remaining_time":34.55181438},
{"learn":[8957.726729],"iteration":156,"passed_time":6.428090187,"remaining_time":34.51515941},
{"learn":[8939.924081],"iteration":157,"passed_time":6.464457594,"remaining_time":34.44983098},
{"learn":[8929.091429],"iteration":158,"passed_time":6.506233571,"remaining_time":34.41347442},
{"learn":[8915.790362],"iteration":159,"passed_time":6.543362758,"remaining_time":34.35265448},
{"learn":[8902.391188],"iteration":160,"passed_time":6.570245481,"remaining_time":34.23873266},
{"learn":[8892.591754],"iteration":161,"passed_time":6.609565141,"remaining_time":34.19021968},
{"learn":[8884.980371],"iteration":162,"passed_time":6.652018717,"remaining_time":34.15791206},
{"learn":[8870.200117],"iteration":163,"passed_time":6.69159453,"remaining_time":34.11081114},
{"learn":[8855.831038],"iteration":164,"passed_time":6.73377892,"remaining_time":34.07700241},
{"learn":[8839.441132],"iteration":165,"passed_time":6.777323372,"remaining_time":34.04992586},
{"learn":[8817.556983],"iteration":166,"passed_time":6.823698445,"remaining_time":34.03677128},
{"learn":[8808.302359],"iteration":167,"passed_time":6.862967548,"remaining_time":33.98802976},
{"learn":[8799.317401],"iteration":168,"passed_time":6.901801174,"remaining_time":33.93725902},
{"learn":[8781.546781],"iteration":169,"passed_time":6.944176355,"remaining_time":33.90391985},
{"learn":[8773.51166],"iteration":170,"passed_time":6.980225038,"remaining_time":33.83980442},
{"learn":[8765.232072],"iteration":171,"passed_time":7.024665141,"remaining_time":33.81641126},
{"learn":[8755.160884],"iteration":172,"passed_time":7.069435956,"remaining_time":33.7943557},
{"learn":[8741.240953],"iteration":173,"passed_time":7.108996272,"remaining_time":33.74730414},
{"learn":[8730.735934],"iteration":174,"passed_time":7.150064338,"remaining_time":33.70744616},
{"learn":[8715.752046],"iteration":175,"passed_time":7.193455872,"remaining_time":33.67845249},
{"learn":[8705.903852],"iteration":176,"passed_time":7.232212112,"remaining_time":33.62774332},
{"learn":[8681.774515],"iteration":177,"passed_time":7.273093063,"remaining_time":33.58698032},
{"learn":[8668.600101],"iteration":178,"passed_time":7.312000791,"remaining_time":33.53716564},
{"learn":[8656.681124],"iteration":179,"passed_time":7.349265878,"remaining_time":33.479989},
{"learn":[8637.597],"iteration":180,"passed_time":7.393763142,"remaining_time":33.45575698},
{"learn":[8627.583939],"iteration":181,"passed_time":7.430004213,"remaining_time":33.39419476},
{"learn":[8614.475096],"iteration":182,"passed_time":7.474136994,"remaining_time":33.36814166},
{"learn":[8602.551195],"iteration":183,"passed_time":7.517371244,"remaining_time":33.33790726},
{"learn":[8590.938921],"iteration":184,"passed_time":7.561786837,"remaining_time":33.31273661},
{"learn":[8583.089999],"iteration":185,"passed_time":7.605094955,"remaining_time":33.28251233},
{"learn":[8569.037645],"iteration":186,"passed_time":7.646617407,"remaining_time":33.24438477},
{"learn":[8551.574989],"iteration":187,"passed_time":7.689809378,"remaining_time":33.21343199},
{"learn":[8539.068233],"iteration":188,"passed_time":7.731591068,"remaining_time":33.17629818},
{"learn":[8533.014793],"iteration":189,"passed_time":7.774016927,"remaining_time":33.14186164},
{"learn":[8518.817233],"iteration":190,"passed_time":7.818071963,"remaining_time":33.11424198},
{"learn":[8510.120177],"iteration":191,"passed_time":7.856114729,"remaining_time":33.06114948},
{"learn":[8501.236444],"iteration":192,"passed_time":7.897831571,"remaining_time":33.02357553},
{"learn":[8491.677799],"iteration":193,"passed_time":7.939261157,"remaining_time":32.98476543},
{"learn":[8483.688935],"iteration":194,"passed_time":7.983115106,"remaining_time":32.95593672},
{"learn":[8466.975154],"iteration":195,"passed_time":8.023136889,"remaining_time":32.911235},
{"learn":[8456.545419],"iteration":196,"passed_time":8.068798797,"remaining_time":32.88957073},
{"learn":[8448.331867],"iteration":197,"passed_time":8.107714725,"remaining_time":32.84033944},
{"learn":[8438.26201],"iteration":198,"passed_time":8.14558972,"remaining_time":32.78702194},
{"learn":[8430.447888],"iteration":199,"passed_time":8.188245903,"remaining_time":32.75298361},
{"learn":[8408.742896],"iteration":200,"passed_time":8.230565954,"remaining_time":32.71752337},
{"learn":[8401.019868],"iteration":201,"passed_time":8.274878886,"remaining_time":32.68986807},
{"learn":[8379.514332],"iteration":202,"passed_time":8.314523318,"remaining_time":32.64371963},
{"learn":[8361.124731],"iteration":203,"passed_time":8.354606353,"remaining_time":32.59934636},
{"learn":[8347.319131],"iteration":204,"passed_time":8.396858322,"remaining_time":32.56342618},
{"learn":[8338.479738],"iteration":205,"passed_time":8.440539397,"remaining_time":32.53295282},
{"learn":[8333.134746],"iteration":206,"passed_time":8.483594016,"remaining_time":32.49995196},
{"learn":[8326.834584],"iteration":207,"passed_time":8.516872279,"remaining_time":32.42962906},
{"learn":[8319.605413],"iteration":208,"passed_time":8.555919599,"remaining_time":32.38149475},
{"learn":[8307.169411],"iteration":209,"passed_time":8.594227509,"remaining_time":32.33066539},
{"learn":[8300.481859],"iteration":210,"passed_time":8.629864094,"remaining_time":32.26996574},
{"learn":[8289.203621],"iteration":211,"passed_time":8.674895284,"remaining_time":32.24442209},
{"learn":[8278.973557],"iteration":212,"passed_time":8.718555271,"remaining_time":32.2136291},
{"learn":[8267.575156],"iteration":213,"passed_time":8.763270562,"remaining_time":32.18659188},
{"learn":[8258.246207],"iteration":214,"passed_time":8.807634602,"remaining_time":32.15810773},
{"learn":[8245.060262],"iteration":215,"passed_time":8.846511464,"remaining_time":32.10956013},
{"learn":[8238.865308],"iteration":216,"passed_time":8.890472012,"remaining_time":32.0794451},
{"learn":[8229.908312],"iteration":217,"passed_time":8.930026426,"remaining_time":32.03339755},
{"learn":[8221.148106],"iteration":218,"passed_time":8.975857324,"remaining_time":32.00979256},
{"learn":[8212.018623],"iteration":219,"passed_time":9.022700543,"remaining_time":31.98957465},
{"learn":[8206.136055],"iteration":220,"passed_time":9.061017947,"remaining_time":31.93906326},
{"learn":[8196.995709],"iteration":221,"passed_time":9.10373395,"remaining_time":31.90407664},
{"learn":[8188.009845],"iteration":222,"passed_time":9.144611325,"remaining_time":31.86261435},
{"learn":[8173.342504],"iteration":223,"passed_time":9.188987181,"remaining_time":31.83327702},
{"learn":[8168.088971],"iteration":224,"passed_time":9.232985242,"remaining_time":31.80250472},
{"learn":[8162.838571],"iteration":225,"passed_time":9.278545043,"remaining_time":31.776964},
{"learn":[8156.912015],"iteration":226,"passed_time":9.32181202,"remaining_time":31.74343917},
{"learn":[8144.78032],"iteration":227,"passed_time":9.364808835,"remaining_time":31.70891412},
{"learn":[8136.647215],"iteration":228,"passed_time":9.409273112,"remaining_time":31.67925576},
{"learn":[8129.05894],"iteration":229,"passed_time":9.448940012,"remaining_time":31.63340787},
{"learn":[8116.305388],"iteration":230,"passed_time":9.49071629,"remaining_time":31.59463561},
{"learn":[8110.706434],"iteration":231,"passed_time":9.53490052,"remaining_time":31.56380862},
{"learn":[8101.892986],"iteration":232,"passed_time":9.575844872,"remaining_time":31.52220179},
{"learn":[8094.951362],"iteration":233,"passed_time":9.612599554,"remaining_time":31.46688572},
{"learn":[8086.918572],"iteration":234,"passed_time":9.653369807,"remaining_time":31.42479959},
{"learn":[8074.412535],"iteration":235,"passed_time":9.692770659,"remaining_time":31.37829146},
{"learn":[8059.955078],"iteration":236,"passed_time":9.728901339,"remaining_time":31.32131528},
{"learn":[8054.033926],"iteration":237,"passed_time":9.775876644,"remaining_time":31.2992353},
{"learn":[8041.8213],"iteration":238,"passed_time":9.820511282,"remaining_time":31.26949408},
{"learn":[8033.438931],"iteration":239,"passed_time":9.86198643,"remaining_time":31.2296237},
{"learn":[8027.393236],"iteration":240,"passed_time":9.904632306,"remaining_time":31.19342705},
{"learn":[8019.964958],"iteration":241,"passed_time":9.948686041,"remaining_time":31.16158686},
{"learn":[8015.042707],"iteration":242,"passed_time":9.994494134,"remaining_time":31.13511136},
{"learn":[8007.873395],"iteration":243,"passed_time":10.03977353,"remaining_time":31.10683931},
{"learn":[8001.514283],"iteration":244,"passed_time":10.06930042,"remaining_time":31.02988496},
{"learn":[7996.392355],"iteration":245,"passed_time":10.11176853,"remaining_time":30.9929816},
{"learn":[7988.060635],"iteration":246,"passed_time":10.15079422,"remaining_time":30.94553865},
{"learn":[7980.561139],"iteration":247,"passed_time":10.19323893,"remaining_time":30.90853095},
{"learn":[7969.867262],"iteration":248,"passed_time":10.23173391,"remaining_time":30.85956692},
{"learn":[7959.857602],"iteration":249,"passed_time":10.27552713,"remaining_time":30.8265814},
{"learn":[7952.290725],"iteration":250,"passed_time":10.31496693,"remaining_time":30.78051886},
{"learn":[7935.269281],"iteration":251,"passed_time":10.35786206,"remaining_time":30.74476515},
{"learn":[7930.577801],"iteration":252,"passed_time":10.39677681,"remaining_time":30.69720267},
{"learn":[7924.010098],"iteration":253,"passed_time":10.43866109,"remaining_time":30.6584298},
{"learn":[7916.584756],"iteration":254,"passed_time":10.48069114,"remaining_time":30.62005844},
{"learn":[7904.946978],"iteration":255,"passed_time":10.52049506,"remaining_time":30.57518876},
{"learn":[7899.394002],"iteration":256,"passed_time":10.5647614,"remaining_time":30.5432596},
{"learn":[7892.047701],"iteration":257,"passed_time":10.60934637,"remaining_time":30.5121512},
{"learn":[7883.873319],"iteration":258,"passed_time":10.65248728,"remaining_time":30.47680725},
{"learn":[7880.97541],"iteration":259,"passed_time":10.69474576,"remaining_time":30.43889177},
{"learn":[7873.618444],"iteration":260,"passed_time":10.73680179,"remaining_time":30.40036981},
{"learn":[7863.566814],"iteration":261,"passed_time":10.77662292,"remaining_time":30.35552562},
{"learn":[7857.675247],"iteration":262,"passed_time":10.81309185,"remaining_time":30.30132584},
{"learn":[7849.732762],"iteration":263,"passed_time":10.85415877,"remaining_time":30.260079},
{"learn":[7844.039865],"iteration":264,"passed_time":10.89815705,"remaining_time":30.2269639},
{"learn":[7834.59781],"iteration":265,"passed_time":10.94134235,"remaining_time":30.19152364},
{"learn":[7828.554061],"iteration":266,"passed_time":10.98070226,"remaining_time":30.14552343},
{"learn":[7814.55404],"iteration":267,"passed_time":11.02264664,"remaining_time":30.10663188},
{"learn":[7779.862253],"iteration":268,"passed_time":11.0660814,"remaining_time":30.07176768},
{"learn":[7774.357737],"iteration":269,"passed_time":11.10130139,"remaining_time":30.01462967},
{"learn":[7763.370812],"iteration":270,"passed_time":11.14328315,"remaining_time":29.97584286},
{"learn":[7756.344391],"iteration":271,"passed_time":11.17948205,"remaining_time":29.92155491},
{"learn":[7751.647792],"iteration":272,"passed_time":11.22334284,"remaining_time":29.8878031},
{"learn":[7744.467573],"iteration":273,"passed_time":11.26935272,"remaining_time":29.8596718},
{"learn":[7738.094011],"iteration":274,"passed_time":11.30858363,"remaining_time":29.81353867},
{"learn":[7734.794189],"iteration":275,"passed_time":11.34638997,"remaining_time":29.76371861},
{"learn":[7725.220577],"iteration":276,"passed_time":11.38950971,"remaining_time":29.72785388},
{"learn":[7716.355046],"iteration":277,"passed_time":11.42703313,"remaining_time":29.67740259},
{"learn":[7711.378441],"iteration":278,"passed_time":11.47031592,"remaining_time":29.64192752},
{"learn":[7707.229018],"iteration":279,"passed_time":11.50950562,"remaining_time":29.5958716},
{"learn":[7698.660605],"iteration":280,"passed_time":11.55266999,"remaining_time":29.56003461},
{"learn":[7690.640205],"iteration":281,"passed_time":11.59536561,"remaining_time":29.52295216},
{"learn":[7680.36878],"iteration":282,"passed_time":11.63779424,"remaining_time":29.48515361},
{"learn":[7674.646148],"iteration":283,"passed_time":11.68171399,"remaining_time":29.45108175},
{"learn":[7669.085766],"iteration":284,"passed_time":11.72005892,"remaining_time":29.40295483},
{"learn":[7659.475628],"iteration":285,"passed_time":11.76162746,"remaining_time":29.36294409},
{"learn":[7654.368508],"iteration":286,"passed_time":11.80228752,"remaining_time":29.32066552},
{"learn":[7649.706513],"iteration":287,"passed_time":11.84076806,"remaining_time":29.27300991},
{"learn":[7642.435578],"iteration":288,"passed_time":11.88342485,"remaining_time":29.23569227},
{"learn":[7638.102307],"iteration":289,"passed_time":11.92823665,"remaining_time":29.20361386},
{"learn":[7628.432026],"iteration":290,"passed_time":11.96465784,"remaining_time":29.15100483},
{"learn":[7621.683825],"iteration":291,"passed_time":12.00609937,"remaining_time":29.11067929},
{"learn":[7617.868411],"iteration":292,"passed_time":12.04868943,"remaining_time":29.07311751},
{"learn":[7614.062228],"iteration":293,"passed_time":12.09047239,"remaining_time":29.03358336},
{"learn":[7600.521629],"iteration":294,"passed_time":12.13060745,"remaining_time":28.99009576},
{"learn":[7595.29497],"iteration":295,"passed_time":12.17218422,"remaining_time":28.95005977},
{"learn":[7583.197964],"iteration":296,"passed_time":12.21598494,"remaining_time":28.91527748},
{"learn":[7576.4137],"iteration":297,"passed_time":12.26052776,"remaining_time":28.88218285},
{"learn":[7568.157245],"iteration":298,"passed_time":12.30002013,"remaining_time":28.83717095},
{"learn":[7564.944838],"iteration":299,"passed_time":12.34275384,"remaining_time":28.79975896},
{"learn":[7559.948009],"iteration":300,"passed_time":12.38526391,"remaining_time":28.76179228},
{"learn":[7552.212417],"iteration":301,"passed_time":12.42800106,"remaining_time":28.72432033},
{"learn":[7545.292261],"iteration":302,"passed_time":12.47204595,"remaining_time":28.68982187},
{"learn":[7538.747193],"iteration":303,"passed_time":12.51611184,"remaining_time":28.65530867},
{"learn":[7534.761747],"iteration":304,"passed_time":12.55812201,"remaining_time":28.61604851},
{"learn":[7529.244153],"iteration":305,"passed_time":12.60382077,"remaining_time":28.58513599},
{"learn":[7525.517125],"iteration":306,"passed_time":12.64764654,"remaining_time":28.5498992},
{"learn":[7520.187016],"iteration":307,"passed_time":12.68723714,"remaining_time":28.50509124},
{"learn":[7516.227016],"iteration":308,"passed_time":12.72463979,"remaining_time":28.45542427},
{"learn":[7508.817811],"iteration":309,"passed_time":12.76728887,"remaining_time":28.41751394},
{"learn":[7502.054695],"iteration":310,"passed_time":12.81128605,"remaining_time":28.38255977},
{"learn":[7491.427876],"iteration":311,"passed_time":12.85074449,"remaining_time":28.33753914},
{"learn":[7484.018616],"iteration":312,"passed_time":12.89204771,"remaining_time":28.29660313},
{"learn":[7479.797641],"iteration":313,"passed_time":12.9340501,"remaining_time":28.25719226},
{"learn":[7473.703205],"iteration":314,"passed_time":12.97344634,"remaining_time":28.21209759},
{"learn":[7469.677469],"iteration":315,"passed_time":13.01695747,"remaining_time":28.17594592},
{"learn":[7463.865465],"iteration":316,"passed_time":13.06370589,"remaining_time":28.14672278},
{"learn":[7459.434496],"iteration":317,"passed_time":13.10658897,"remaining_time":28.10909961},
{"learn":[7456.561119],"iteration":318,"passed_time":13.1460933,"remaining_time":28.06423052},
{"learn":[7451.739085],"iteration":319,"passed_time":13.18827356,"remaining_time":28.02508131},
{"learn":[7445.964791],"iteration":320,"passed_time":13.23188068,"remaining_time":27.98893141},
{"learn":[7439.856236],"iteration":321,"passed_time":13.27255077,"remaining_time":27.94655101},
{"learn":[7434.856215],"iteration":322,"passed_time":13.3002677,"remaining_time":27.87703169},
{"learn":[7412.106649],"iteration":323,"passed_time":13.34045461,"remaining_time":27.83378801},
{"learn":[7406.349176],"iteration":324,"passed_time":13.38009825,"remaining_time":27.78943482},
{"learn":[7402.506476],"iteration":325,"passed_time":13.42246351,"remaining_time":27.75073745},
{"learn":[7397.910066],"iteration":326,"passed_time":13.46587581,"remaining_time":27.71417255},
{"learn":[7394.595813],"iteration":327,"passed_time":13.51154365,"remaining_time":27.68218699},
{"learn":[7387.284133],"iteration":328,"passed_time":13.55521873,"remaining_time":27.646054},
{"learn":[7377.691942],"iteration":329,"passed_time":13.59404565,"remaining_time":27.60003207},
{"learn":[7372.652977],"iteration":330,"passed_time":13.63793787,"remaining_time":27.56429135},
{"learn":[7367.124513],"iteration":331,"passed_time":13.67797892,"remaining_time":27.52075276},
{"learn":[7359.534444],"iteration":332,"passed_time":13.7229053,"remaining_time":27.48702052},
{"learn":[7355.43716],"iteration":333,"passed_time":13.76817575,"remaining_time":27.45390733},
{"learn":[7349.18401],"iteration":334,"passed_time":13.81405748,"remaining_time":27.42193499},
{"learn":[7342.626659],"iteration":335,"passed_time":13.85120386,"remaining_time":27.37261714},
{"learn":[7336.480682],"iteration":336,"passed_time":13.89686899,"remaining_time":27.34013098},
{"learn":[7330.267142],"iteration":337,"passed_time":13.93549745,"remaining_time":27.29378495},
{"learn":[7321.665729],"iteration":338,"passed_time":13.97744041,"remaining_time":27.25394723},
{"learn":[7317.984831],"iteration":339,"passed_time":14.01762204,"remaining_time":27.21067809},
{"learn":[7312.369872],"iteration":340,"passed_time":14.05650242,"remaining_time":27.16491231},
{"learn":[7306.690567],"iteration":341,"passed_time":14.10078256,"remaining_time":27.12957581},
{"learn":[7302.98731],"iteration":342,"passed_time":14.13974416,"remaining_time":27.08399975},
{"learn":[7297.758264],"iteration":343,"passed_time":14.17986572,"remaining_time":27.04067416},
{"learn":[7292.66958],"iteration":344,"passed_time":14.21867371,"remaining_time":26.99487327},
{"learn":[7287.920859],"iteration":345,"passed_time":14.25651036,"remaining_time":26.94727681},
{"learn":[7281.617882],"iteration":346,"passed_time":14.29852146,"remaining_time":26.90759226},
{"learn":[7276.215671],"iteration":347,"passed_time":14.33998401,"remaining_time":26.86686659},
{"learn":[7272.662739],"iteration":348,"passed_time":14.37868518,"remaining_time":26.82098582},
{"learn":[7262.909408],"iteration":349,"passed_time":14.42057448,"remaining_time":26.7810669},
{"learn":[7257.933596],"iteration":350,"passed_time":14.45845145,"remaining_time":26.73371792},
{"learn":[7248.297841],"iteration":351,"passed_time":14.49941519,"remaining_time":26.69210523},
{"learn":[7244.104251],"iteration":352,"passed_time":14.5437989,"remaining_time":26.65676456},
{"learn":[7239.34025],"iteration":353,"passed_time":14.58662451,"remaining_time":26.61852947},
{"learn":[7235.494428],"iteration":354,"passed_time":14.62563615,"remaining_time":26.57333892},
{"learn":[7229.489203],"iteration":355,"passed_time":14.66749408,"remaining_time":26.53333198},
{"learn":[7225.595679],"iteration":356,"passed_time":14.70700557,"remaining_time":26.48908847},
{"learn":[7220.694306],"iteration":357,"passed_time":14.74482271,"remaining_time":26.4418329},
{"learn":[7214.677246],"iteration":358,"passed_time":14.7786558,"remaining_time":26.38751635},
{"learn":[7211.510992],"iteration":359,"passed_time":14.81591131,"remaining_time":26.33939789},
{"learn":[7209.312865],"iteration":360,"passed_time":14.85327848,"remaining_time":26.29153725},
{"learn":[7205.935997],"iteration":361,"passed_time":14.89202823,"remaining_time":26.2461713},
{"learn":[7201.012477],"iteration":362,"passed_time":14.93349129,"remaining_time":26.20560317},
{"learn":[7198.802772],"iteration":363,"passed_time":14.97600339,"remaining_time":26.16686307},
{"learn":[7194.537846],"iteration":364,"passed_time":15.01534572,"remaining_time":26.12258776},
{"learn":[7190.171308],"iteration":365,"passed_time":15.05691387,"remaining_time":26.08219507},
{"learn":[7177.083856],"iteration":366,"passed_time":15.09805508,"remaining_time":26.04105959},
{"learn":[7175.076991],"iteration":367,"passed_time":15.13920721,"remaining_time":25.99994282},
{"learn":[7171.331292],"iteration":368,"passed_time":15.17257606,"remaining_time":25.94551625},
{"learn":[7166.587718],"iteration":369,"passed_time":15.20994047,"remaining_time":25.89800675},
{"learn":[7162.059528],"iteration":370,"passed_time":15.24460998,"remaining_time":25.84598295},
{"learn":[7158.571021],"iteration":371,"passed_time":15.28152286,"remaining_time":25.79783967},
{"learn":[7155.462299],"iteration":372,"passed_time":15.31891696,"remaining_time":25.7505655},
{"learn":[7148.869514],"iteration":373,"passed_time":15.36141714,"remaining_time":25.71189072},
{"learn":[7142.983446],"iteration":374,"passed_time":15.40344624,"remaining_time":25.67241039},
{"learn":[7139.702639],"iteration":375,"passed_time":15.44379545,"remaining_time":25.63012862},
{"learn":[7127.09158],"iteration":376,"passed_time":15.49192931,"remaining_time":25.60072138},
{"learn":[7121.118116],"iteration":377,"passed_time":15.53438322,"remaining_time":25.56186868},
{"learn":[7109.948114],"iteration":378,"passed_time":15.57164718,"remaining_time":25.51449314},
{"learn":[7106.786484],"iteration":379,"passed_time":15.61191503,"remaining_time":25.4720719},
{"learn":[7102.276553],"iteration":380,"passed_time":15.6493755,"remaining_time":25.42510088},
{"learn":[7096.809398],"iteration":381,"passed_time":15.69379285,"remaining_time":25.38943451},
{"learn":[7090.596313],"iteration":382,"passed_time":15.73738842,"remaining_time":25.35239858},
{"learn":[7082.808648],"iteration":383,"passed_time":15.77755172,"remaining_time":25.30982254},
{"learn":[7079.773859],"iteration":384,"passed_time":15.81347217,"remaining_time":25.26048151},
{"learn":[7076.257823],"iteration":385,"passed_time":15.85596192,"remaining_time":25.22165963},
{"learn":[7068.517547],"iteration":386,"passed_time":15.89316064,"remaining_time":25.17443791},
{"learn":[7066.926801],"iteration":387,"passed_time":15.93331003,"remaining_time":25.131922},
{"learn":[7059.908566],"iteration":388,"passed_time":15.96902153,"remaining_time":25.0824477},
{"learn":[7056.73889],"iteration":389,"passed_time":16.0066514,"remaining_time":25.0360445},
{"learn":[7051.840443],"iteration":390,"passed_time":16.04264166,"remaining_time":24.98713241},
{"learn":[7046.572068],"iteration":391,"passed_time":16.08418294,"remaining_time":24.94689599},
{"learn":[7039.915306],"iteration":392,"passed_time":16.12471084,"remaining_time":24.90508774},
{"learn":[7031.379661],"iteration":393,"passed_time":16.165468,"remaining_time":24.8636386},
{"learn":[7025.132254],"iteration":394,"passed_time":16.20601197,"remaining_time":24.82186644},
{"learn":[7022.808246],"iteration":395,"passed_time":16.24506769,"remaining_time":24.77783052},
{"learn":[7019.228154],"iteration":396,"passed_time":16.28826362,"remaining_time":24.74010822},
{"learn":[7010.730996],"iteration":397,"passed_time":16.32993138,"remaining_time":24.70004696},
{"learn":[7008.068066],"iteration":398,"passed_time":16.37067365,"remaining_time":24.65858361},
{"learn":[7002.870241],"iteration":399,"passed_time":16.40626746,"remaining_time":24.60940119},
{"learn":[6999.403593],"iteration":400,"passed_time":16.44641895,"remaining_time":24.56709465},
{"learn":[6996.011914],"iteration":401,"passed_time":16.48731577,"remaining_time":24.52590754},
{"learn":[6992.983727],"iteration":402,"passed_time":16.52779982,"remaining_time":24.4841104},
{"learn":[6988.689694],"iteration":403,"passed_time":16.56396289,"remaining_time":24.43594525},
{"learn":[6986.38831],"iteration":404,"passed_time":16.60158945,"remaining_time":24.38998944},
{"learn":[6983.512237],"iteration":405,"passed_time":16.64238863,"remaining_time":24.34871637},
{"learn":[6981.305899],"iteration":406,"passed_time":16.68305985,"remaining_time":24.30725919},
{"learn":[6977.531445],"iteration":407,"passed_time":16.72022472,"remaining_time":24.26071821},
{"learn":[6973.656977],"iteration":408,"passed_time":16.75638964,"remaining_time":24.21277819},
{"learn":[6971.807997],"iteration":409,"passed_time":16.79679665,"remaining_time":24.17100006},
{"learn":[6968.698851],"iteration":410,"passed_time":16.83349394,"remaining_time":24.12391224},
{"learn":[6965.148801],"iteration":411,"passed_time":16.87427258,"remaining_time":24.0826997},
{"learn":[6957.557183],"iteration":412,"passed_time":16.91526879,"remaining_time":24.0417985},
{"learn":[6950.883804],"iteration":413,"passed_time":16.95660525,"remaining_time":24.00137844},
{"learn":[6948.046135],"iteration":414,"passed_time":16.9945946,"remaining_time":23.95623576},
{"learn":[6939.172698],"iteration":415,"passed_time":17.03562885,"remaining_time":23.91540204},
{"learn":[6933.512597],"iteration":416,"passed_time":17.07719024,"remaining_time":23.87530434},
{"learn":[6930.682555],"iteration":417,"passed_time":17.11824526,"remaining_time":23.83449459},
{"learn":[6928.332285],"iteration":418,"passed_time":17.15812718,"remaining_time":23.79205702},
{"learn":[6924.254167],"iteration":419,"passed_time":17.19844663,"remaining_time":23.75023582},
{"learn":[6921.482047],"iteration":420,"passed_time":17.23558941,"remaining_time":23.7040529},
{"learn":[6916.57365],"iteration":421,"passed_time":17.27790769,"remaining_time":23.66500153},
{"learn":[6913.669423],"iteration":422,"passed_time":17.31706785,"remaining_time":23.62162683},
{"learn":[6909.782224],"iteration":423,"passed_time":17.35730982,"remaining_time":23.57974164},
{"learn":[6906.411073],"iteration":424,"passed_time":17.39428438,"remaining_time":23.53344357},
{"learn":[6903.527532],"iteration":425,"passed_time":17.43445413,"remaining_time":23.49149453},
{"learn":[6898.570263],"iteration":426,"passed_time":17.47522135,"remaining_time":23.45035558},
{"learn":[6895.799717],"iteration":427,"passed_time":17.51740124,"remaining_time":23.41110632},
{"learn":[6891.44275],"iteration":428,"passed_time":17.55709597,"remaining_time":23.36853566},
{"learn":[6886.92615],"iteration":429,"passed_time":17.59560698,"remaining_time":23.32440925},
{"learn":[6885.068988],"iteration":430,"passed_time":17.63258249,"remaining_time":23.27828175},
{"learn":[6878.743334],"iteration":431,"passed_time":17.67308358,"remaining_time":23.23683211},
{"learn":[6874.991915],"iteration":432,"passed_time":17.71355871,"remaining_time":23.19535286},
{"learn":[6868.416163],"iteration":433,"passed_time":17.75096847,"remaining_time":23.14988054},
{"learn":[6865.802358],"iteration":434,"passed_time":17.78118564,"remaining_time":23.09510319},
{"learn":[6863.047813],"iteration":435,"passed_time":17.81862221,"remaining_time":23.04977735},
{"learn":[6858.019935],"iteration":436,"passed_time":17.85482769,"remaining_time":23.00290157},
{"learn":[6855.502148],"iteration":437,"passed_time":17.89158417,"remaining_time":22.95678151},
{"learn":[6852.625587],"iteration":438,"passed_time":17.92952797,"remaining_time":22.91222139},
{"learn":[6849.692461],"iteration":439,"passed_time":17.96432444,"remaining_time":22.86368565},
{"learn":[6846.649651],"iteration":440,"passed_time":18.00587517,"remaining_time":22.82377375},
{"learn":[6837.985934],"iteration":441,"passed_time":18.04292897,"remaining_time":22.7781773},
{"learn":[6832.732331],"iteration":442,"passed_time":18.08358012,"remaining_time":22.7371425},
{"learn":[6827.927029],"iteration":443,"passed_time":18.12403258,"remaining_time":22.69586062},
{"learn":[6823.295048],"iteration":444,"passed_time":18.16316767,"remaining_time":22.65293945},
{"learn":[6820.301613],"iteration":445,"passed_time":18.19871104,"remaining_time":22.60557381},
{"learn":[6816.02679],"iteration":446,"passed_time":18.2370611,"remaining_time":22.56173331},
{"learn":[6811.353329],"iteration":447,"passed_time":18.27708305,"remaining_time":22.51997733},
{"learn":[6805.187109],"iteration":448,"passed_time":18.31010334,"remaining_time":22.46963684},
{"learn":[6802.308844],"iteration":449,"passed_time":18.34664257,"remaining_time":22.42367425},
{"learn":[6800.472873],"iteration":450,"passed_time":18.38529254,"remaining_time":22.38032285},
{"learn":[6796.43234],"iteration":451,"passed_time":18.42512237,"remaining_time":22.33842269},
{"learn":[6794.210813],"iteration":452,"passed_time":18.45974431,"remaining_time":22.29024312},
{"learn":[6792.49174],"iteration":453,"passed_time":18.49974772,"remaining_time":22.24859528},
{"learn":[6791.034219],"iteration":454,"passed_time":18.53907271,"remaining_time":22.20614203},
{"learn":[6787.476266],"iteration":455,"passed_time":18.57711682,"remaining_time":22.16217445},
{"learn":[6782.220799],"iteration":456,"passed_time":18.61799433,"remaining_time":22.12159939},
{"learn":[6775.254568],"iteration":457,"passed_time":18.65301337,"remaining_time":22.07409006},
{"learn":[6765.636967],"iteration":458,"passed_time":18.69535177,"remaining_time":22.03526211},
{"learn":[6762.344779],"iteration":459,"passed_time":18.73611477,"remaining_time":21.99456952},
{"learn":[6758.600517],"iteration":460,"passed_time":18.77564331,"remaining_time":21.95243329},
{"learn":[6754.600551],"iteration":461,"passed_time":18.81491644,"remaining_time":21.91001091},
{"learn":[6752.372985],"iteration":462,"passed_time":18.85123433,"remaining_time":21.86417459},
{"learn":[6749.319912],"iteration":463,"passed_time":18.88601583,"remaining_time":21.8166045},
{"learn":[6746.252464],"iteration":464,"passed_time":18.92436058,"remaining_time":21.77318905},
{"learn":[6743.388915],"iteration":465,"passed_time":18.96435611,"remaining_time":21.73168705},
{"learn":[6739.819905],"iteration":466,"passed_time":18.99958614,"remaining_time":21.68475249},
{"learn":[6736.114417],"iteration":467,"passed_time":19.04203186,"remaining_time":21.64607041},
{"learn":[6731.307478],"iteration":468,"passed_time":19.08150971,"remaining_time":21.60401206},
{"learn":[6727.669598],"iteration":469,"passed_time":19.1094242,"remaining_time":21.54892517},
{"learn":[6723.66306],"iteration":470,"passed_time":19.14944432,"remaining_time":21.50754999},
{"learn":[6718.797917],"iteration":471,"passed_time":19.19001382,"remaining_time":21.46679512},
{"learn":[6715.677026],"iteration":472,"passed_time":19.22606887,"remaining_time":21.4210112},
{"learn":[6713.662021],"iteration":473,"passed_time":19.26618048,"remaining_time":21.3797699},
{"learn":[6711.897751],"iteration":474,"passed_time":19.30554914,"remaining_time":21.3377122},
{"learn":[6710.026058],"iteration":475,"passed_time":19.34738451,"remaining_time":21.29838127},
{"learn":[6706.860474],"iteration":476,"passed_time":19.38785647,"remaining_time":21.25754494},
{"learn":[6703.409401],"iteration":477,"passed_time":19.42798504,"remaining_time":21.21633512},
{"learn":[6700.186408],"iteration":478,"passed_time":19.46731269,"remaining_time":21.17425869},
{"learn":[6697.006262],"iteration":479,"passed_time":19.50620959,"remaining_time":21.13172705},
{"learn":[6692.756522],"iteration":480,"passed_time":19.54671548,"remaining_time":21.09094665},
{"learn":[6690.568268],"iteration":481,"passed_time":19.58960467,"remaining_time":21.05272867},
{"learn":[6686.688088],"iteration":482,"passed_time":19.6321396,"remaining_time":21.01411216},
{"learn":[6684.665994],"iteration":483,"passed_time":19.66954018,"remaining_time":20.97000565},
{"learn":[6683.043793],"iteration":484,"passed_time":19.70411294,"remaining_time":20.92292405},
{"learn":[6678.202725],"iteration":485,"passed_time":19.74140575,"remaining_time":20.87877069},
{"learn":[6675.787996],"iteration":486,"passed_time":19.78090934,"remaining_time":20.83697432},
{"learn":[6671.52825],"iteration":487,"passed_time":19.82434783,"remaining_time":20.79931575},
{"learn":[6670.50943],"iteration":488,"passed_time":19.86338397,"remaining_time":20.75703315},
{"learn":[6665.982798],"iteration":489,"passed_time":19.90007818,"remaining_time":20.71232627},
{"learn":[6663.177207],"iteration":490,"passed_time":19.93435629,"remaining_time":20.66514736},
{"learn":[6660.306474],"iteration":491,"passed_time":19.96923848,"remaining_time":20.61864461},
{"learn":[6658.306338],"iteration":492,"passed_time":20.0072265,"remaining_time":20.57538303},
{"learn":[6655.70477],"iteration":493,"passed_time":20.04733412,"remaining_time":20.5343139},
{"learn":[6653.176383],"iteration":494,"passed_time":20.08886765,"remaining_time":20.49470336},
{"learn":[6651.12083],"iteration":495,"passed_time":20.12753038,"remaining_time":20.45216797},
{"learn":[6647.84712],"iteration":496,"passed_time":20.16812994,"remaining_time":20.41160837},
{"learn":[6645.648107],"iteration":497,"passed_time":20.20663391,"remaining_time":20.36893619},
{"learn":[6642.627852],"iteration":498,"passed_time":20.23850942,"remaining_time":20.31962569},
{"learn":[6639.521434],"iteration":499,"passed_time":20.27532361,"remaining_time":20.27532361},
{"learn":[6636.415427],"iteration":500,"passed_time":20.31751264,"remaining_time":20.23640481},
{"learn":[6631.707966],"iteration":501,"passed_time":20.3588783,"remaining_time":20.19665617},
{"learn":[6628.273431],"iteration":502,"passed_time":20.39715693,"remaining_time":20.15385088},
{"learn":[6626.1483],"iteration":503,"passed_time":20.43768902,"remaining_time":20.11328126},
{"learn":[6624.214358],"iteration":504,"passed_time":20.47810671,"remaining_time":20.07259965},
{"learn":[6619.91693],"iteration":505,"passed_time":20.51643829,"remaining_time":20.02988245},
{"learn":[6616.141333],"iteration":506,"passed_time":20.55472611,"remaining_time":19.98713999},
{"learn":[6612.376654],"iteration":507,"passed_time":20.59524296,"remaining_time":19.94657389},
{"learn":[6607.651901],"iteration":508,"passed_time":20.62912916,"remaining_time":19.89961182},
{"learn":[6599.94975],"iteration":509,"passed_time":20.67164392,"remaining_time":19.86099122},
{"learn":[6596.390229],"iteration":510,"passed_time":20.70873444,"remaining_time":19.81716466},
{"learn":[6589.175063],"iteration":511,"passed_time":20.74431895,"remaining_time":19.771929},
{"learn":[6587.546604],"iteration":512,"passed_time":20.7859335,"remaining_time":19.73245539},
{"learn":[6585.047435],"iteration":513,"passed_time":20.8279237,"remaining_time":19.69332863},
{"learn":[6581.712342],"iteration":514,"passed_time":20.87011296,"remaining_time":19.65437822},
{"learn":[6577.669124],"iteration":515,"passed_time":20.9062375,"remaining_time":19.60972664},
{"learn":[6575.834506],"iteration":516,"passed_time":20.94230589,"remaining_time":19.5650556},
{"learn":[6574.162562],"iteration":517,"passed_time":20.98131073,"remaining_time":19.52315014},
{"learn":[6573.195297],"iteration":518,"passed_time":21.0148866,"remaining_time":19.47622438},
{"learn":[6569.553413],"iteration":519,"passed_time":21.0547552,"remaining_time":19.43515865},
{"learn":[6568.150162],"iteration":520,"passed_time":21.09215925,"remaining_time":19.39183164},
{"learn":[6566.286309],"iteration":521,"passed_time":21.13389131,"remaining_time":19.35249051},
{"learn":[6564.635826],"iteration":522,"passed_time":21.17553234,"remaining_time":19.31305722},
{"learn":[6562.280181],"iteration":523,"passed_time":21.2112699,"remaining_time":19.26825281},
{"learn":[6559.139557],"iteration":524,"passed_time":21.24770498,"remaining_time":19.22411403},
{"learn":[6555.713729],"iteration":525,"passed_time":21.28461948,"remaining_time":19.18043656},
{"learn":[6552.075718],"iteration":526,"passed_time":21.3207329,"remaining_time":19.13606577},
{"learn":[6550.424522],"iteration":527,"passed_time":21.37251325,"remaining_time":19.10573154},
{"learn":[6531.959472],"iteration":528,"passed_time":21.41414597,"remaining_time":19.0662812},
{"learn":[6529.495512],"iteration":529,"passed_time":21.45261753,"remaining_time":19.02401932},
{"learn":[6526.452733],"iteration":530,"passed_time":21.49160385,"remaining_time":18.98222638},
{"learn":[6524.199726],"iteration":531,"passed_time":21.53033753,"remaining_time":18.94022174},
{"learn":[6522.199159],"iteration":532,"passed_time":21.56942217,"remaining_time":18.89853688},
{"learn":[6518.734927],"iteration":533,"passed_time":21.60562368,"remaining_time":18.85434576},
{"learn":[6516.37191],"iteration":534,"passed_time":21.64397013,"remaining_time":18.81204881},
{"learn":[6514.036412],"iteration":535,"passed_time":21.67968645,"remaining_time":18.76748977},
{"learn":[6511.432984],"iteration":536,"passed_time":21.72298172,"remaining_time":18.72949821},
{"learn":[6509.711255],"iteration":537,"passed_time":21.75939849,"remaining_time":18.68558012},
{"learn":[6507.574308],"iteration":538,"passed_time":21.80563463,"remaining_time":18.65008824},
{"learn":[6504.362593],"iteration":539,"passed_time":21.85883058,"remaining_time":18.62048531},
{"learn":[6498.846038],"iteration":540,"passed_time":21.89815316,"remaining_time":18.57902459},
{"learn":[6496.057198],"iteration":541,"passed_time":21.93803895,"remaining_time":18.53804768},
{"learn":[6494.28595],"iteration":542,"passed_time":21.97545072,"remaining_time":18.4949926},
{"learn":[6492.420608],"iteration":543,"passed_time":22.0105686,"remaining_time":18.45003545},
{"learn":[6489.621404],"iteration":544,"passed_time":22.04824646,"remaining_time":18.40725163},
{"learn":[6488.315469],"iteration":545,"passed_time":22.07724251,"remaining_time":18.35726758},
{"learn":[6486.753111],"iteration":546,"passed_time":22.116545,"remaining_time":18.31589558},
{"learn":[6484.422264],"iteration":547,"passed_time":22.15531967,"remaining_time":18.27409579},
{"learn":[6479.030612],"iteration":548,"passed_time":22.19892458,"remaining_time":18.23627502},
{"learn":[6476.381178],"iteration":549,"passed_time":22.2384706,"remaining_time":18.19511231},
{"learn":[6474.635008],"iteration":550,"passed_time":22.27156864,"remaining_time":18.14870113},
{"learn":[6466.592922],"iteration":551,"passed_time":22.30994993,"remaining_time":18.10662603},
{"learn":[6463.960276],"iteration":552,"passed_time":22.34764201,"remaining_time":18.0640072},
{"learn":[6460.310769],"iteration":553,"passed_time":22.38355189,"remaining_time":18.01997138},
{"learn":[6458.161118],"iteration":554,"passed_time":22.42202005,"remaining_time":17.97801608},
{"learn":[6455.006777],"iteration":555,"passed_time":22.46174484,"remaining_time":17.93707682},
{"learn":[6452.017781],"iteration":556,"passed_time":22.50060503,"remaining_time":17.89545427},
{"learn":[6450.263176],"iteration":557,"passed_time":22.53913737,"remaining_time":17.85358193},
{"learn":[6447.672936],"iteration":558,"passed_time":22.57832301,"remaining_time":17.81223693},
{"learn":[6446.462918],"iteration":559,"passed_time":22.61663302,"remaining_time":17.77021166},
{"learn":[6444.857536],"iteration":560,"passed_time":22.65791751,"remaining_time":17.73052725},
{"learn":[6442.680378],"iteration":561,"passed_time":22.69791082,"remaining_time":17.68983085},
{"learn":[6440.798547],"iteration":562,"passed_time":22.73316907,"remaining_time":17.64546161},
{"learn":[6438.348159],"iteration":563,"passed_time":22.77152485,"remaining_time":17.60351921},
{"learn":[6434.716953],"iteration":564,"passed_time":22.81174858,"remaining_time":17.56302767},
{"learn":[6433.546063],"iteration":565,"passed_time":22.85306951,"remaining_time":17.52337839},
{"learn":[6430.773032],"iteration":566,"passed_time":22.88975099,"remaining_time":17.48018021},
{"learn":[6427.86578],"iteration":567,"passed_time":22.93093809,"remaining_time":17.44043179},
{"learn":[6425.566771],"iteration":568,"passed_time":22.97042655,"remaining_time":17.39939164},
{"learn":[6419.522005],"iteration":569,"passed_time":23.00486254,"remaining_time":17.35454542},
{"learn":[6418.075391],"iteration":570,"passed_time":23.03866192,"remaining_time":17.30925738},
{"learn":[6415.882101],"iteration":571,"passed_time":23.07863922,"remaining_time":17.26863214},
{"learn":[6414.445279],"iteration":572,"passed_time":23.11345396,"remaining_time":17.22416202},
{"learn":[6413.075683],"iteration":573,"passed_time":23.1506432,"remaining_time":17.18148781},
{"learn":[6410.887023],"iteration":574,"passed_time":23.18811786,"remaining_time":17.13904364},
{"learn":[6407.870853],"iteration":575,"passed_time":23.22305259,"remaining_time":17.09474705},
{"learn":[6406.355965],"iteration":576,"passed_time":23.26391901,"remaining_time":17.05483144},
{"learn":[6402.744202],"iteration":577,"passed_time":23.29803467,"remaining_time":17.00998379},
{"learn":[6400.556911],"iteration":578,"passed_time":23.33700226,"remaining_time":16.96870112},
{"learn":[6394.905748],"iteration":579,"passed_time":23.37579021,"remaining_time":16.92729636},
{"learn":[6392.730807],"iteration":580,"passed_time":23.41567222,"remaining_time":16.88668961},
{"learn":[6389.547161],"iteration":581,"passed_time":23.45463059,"remaining_time":16.84542197},
{"learn":[6381.318208],"iteration":582,"passed_time":23.49085401,"remaining_time":16.80220604},
{"learn":[6377.271684],"iteration":583,"passed_time":23.52895209,"remaining_time":16.76034944},
{"learn":[6373.765316],"iteration":584,"passed_time":23.56170815,"remaining_time":16.71471603},
{"learn":[6370.968956],"iteration":585,"passed_time":23.59820783,"remaining_time":16.6717714},
{"learn":[6368.586513],"iteration":586,"passed_time":23.63641139,"remaining_time":16.63004753},
{"learn":[6365.099425],"iteration":587,"passed_time":23.67558577,"remaining_time":16.58901588},
{"learn":[6363.640569],"iteration":588,"passed_time":23.71102647,"remaining_time":16.54538519},
{"learn":[6361.438152],"iteration":589,"passed_time":23.75144421,"remaining_time":16.50524089},
{"learn":[6358.667328],"iteration":590,"passed_time":23.79161651,"remaining_time":16.46492581},
{"learn":[6354.523352],"iteration":591,"passed_time":23.82838764,"remaining_time":16.42226715},
{"learn":[6352.116972],"iteration":592,"passed_time":23.86846325,"remaining_time":16.38189636},
{"learn":[6348.859299],"iteration":593,"passed_time":23.90338053,"remaining_time":16.33800083},
{"learn":[6347.289015],"iteration":594,"passed_time":23.94584232,"remaining_time":16.29927082},
{"learn":[6344.833761],"iteration":595,"passed_time":23.99025527,"remaining_time":16.26185089},
{"learn":[6342.849583],"iteration":596,"passed_time":24.03331306,"remaining_time":16.22349274},
{"learn":[6341.605617],"iteration":597,"passed_time":24.07331924,"remaining_time":16.18306745},
{"learn":[6338.701176],"iteration":598,"passed_time":24.11632643,"remaining_time":16.14465259},
{"learn":[6335.822084],"iteration":599,"passed_time":24.15420181,"remaining_time":16.1028012},
{"learn":[6332.1001],"iteration":600,"passed_time":24.19124282,"remaining_time":16.06040913},
{"learn":[6330.888786],"iteration":601,"passed_time":24.23026189,"remaining_time":16.01934258},
{"learn":[6328.502723],"iteration":602,"passed_time":24.26862591,"remaining_time":15.97785155},
{"learn":[6326.009933],"iteration":603,"passed_time":24.30707435,"remaining_time":15.93642623},
{"learn":[6324.032167],"iteration":604,"passed_time":24.34675244,"remaining_time":15.89581358},
{"learn":[6320.519916],"iteration":605,"passed_time":24.38543833,"remaining_time":15.85455891},
{"learn":[6318.002173],"iteration":606,"passed_time":24.42113385,"remaining_time":15.81137661},
{"learn":[6315.860094],"iteration":607,"passed_time":24.45218361,"remaining_time":15.76522364},
{"learn":[6310.450613],"iteration":608,"passed_time":24.49174884,"remaining_time":15.72458751},
{"learn":[6308.992763],"iteration":609,"passed_time":24.52974768,"remaining_time":15.68295344},
{"learn":[6305.441165],"iteration":610,"passed_time":24.56864133,"remaining_time":15.64190095},
{"learn":[6302.438493],"iteration":611,"passed_time":24.60646554,"remaining_time":15.6001775},
{"learn":[6300.562828],"iteration":612,"passed_time":24.6465684,"remaining_time":15.55990533},
{"learn":[6298.591949],"iteration":613,"passed_time":24.68562008,"remaining_time":15.51897288},
{"learn":[6296.417762],"iteration":614,"passed_time":24.72617595,"remaining_time":15.4789882},
{"learn":[6295.258449],"iteration":615,"passed_time":24.76789782,"remaining_time":15.43972851},
{"learn":[6293.389235],"iteration":616,"passed_time":24.81076077,"remaining_time":15.40116917},
{"learn":[6291.85831],"iteration":617,"passed_time":24.84911472,"remaining_time":15.35980878},
{"learn":[6289.673273],"iteration":618,"passed_time":24.89279689,"remaining_time":15.32173766},
{"learn":[6284.57473],"iteration":619,"passed_time":24.93418914,"remaining_time":15.28224496},
{"learn":[6283.257054],"iteration":620,"passed_time":24.97228493,"remaining_time":15.24073428},
{"learn":[6281.772592],"iteration":621,"passed_time":25.00608237,"remaining_time":15.19662241},
{"learn":[6279.319963],"iteration":622,"passed_time":25.04406933,"remaining_time":15.15507887},
{"learn":[6274.932099],"iteration":623,"passed_time":25.08317527,"remaining_time":15.114221},
{"learn":[6273.978656],"iteration":624,"passed_time":25.12651674,"remaining_time":15.07591005},
{"learn":[6271.708697],"iteration":625,"passed_time":25.16514341,"remaining_time":15.03476619},
{"learn":[6269.637241],"iteration":626,"passed_time":25.20631184,"remaining_time":14.99514245},
{"learn":[6266.674037],"iteration":627,"passed_time":25.24846334,"remaining_time":14.95609612},
{"learn":[6265.372241],"iteration":628,"passed_time":25.29302104,"remaining_time":14.91845915},
{"learn":[6263.539702],"iteration":629,"passed_time":25.32325257,"remaining_time":14.87238643},
{"learn":[6261.840304],"iteration":630,"passed_time":25.35745345,"remaining_time":14.82868514},
{"learn":[6260.229072],"iteration":631,"passed_time":25.39696435,"remaining_time":14.78810582},
{"learn":[6258.157812],"iteration":632,"passed_time":25.44039478,"remaining_time":14.74980234},
{"learn":[6256.293866],"iteration":633,"passed_time":25.47961489,"remaining_time":14.70905213},
{"learn":[6253.980415],"iteration":634,"passed_time":25.51665221,"remaining_time":14.66705206},
{"learn":[6250.209581],"iteration":635,"passed_time":25.55320904,"remaining_time":14.6247926},
{"learn":[6248.055047],"iteration":636,"passed_time":25.5946297,"remaining_time":14.58532273},
{"learn":[6246.076645],"iteration":637,"passed_time":25.63225059,"remaining_time":14.54369078},
{"learn":[6244.535399],"iteration":638,"passed_time":25.67250525,"remaining_time":14.5035593},
{"learn":[6242.361101],"iteration":639,"passed_time":25.71094819,"remaining_time":14.46240836},
{"learn":[6241.197919],"iteration":640,"passed_time":25.75096183,"remaining_time":14.42214555},
{"learn":[6239.679208],"iteration":641,"passed_time":25.79049439,"remaining_time":14.38161525},
{"learn":[6237.93694],"iteration":642,"passed_time":25.83284236,"remaining_time":14.3426512},
{"learn":[6236.157024],"iteration":643,"passed_time":25.87140821,"remaining_time":14.3015859},
{"learn":[6226.556671],"iteration":644,"passed_time":25.91047581,"remaining_time":14.26080451},
{"learn":[6224.453942],"iteration":645,"passed_time":25.94576542,"remaining_time":14.21795814},
{"learn":[6222.387701],"iteration":646,"passed_time":25.98352059,"remaining_time":14.17648032},
{"learn":[6216.843561],"iteration":647,"passed_time":26.02020096,"remaining_time":14.13443015},
{"learn":[6215.09581],"iteration":648,"passed_time":26.05495733,"remaining_time":14.09135597},
{"learn":[6213.683981],"iteration":649,"passed_time":26.09322571,"remaining_time":14.05019846},
{"learn":[6210.792274],"iteration":650,"passed_time":26.13576628,"remaining_time":14.01134014},
{"learn":[6208.503265],"iteration":651,"passed_time":26.17888794,"remaining_time":13.97278068},
{"learn":[6206.162443],"iteration":652,"passed_time":26.21685394,"remaining_time":13.93146756},
{"learn":[6200.890574],"iteration":653,"passed_time":26.26088789,"remaining_time":13.89337494},
{"learn":[6198.424293],"iteration":654,"passed_time":26.30435052,"remaining_time":13.85496325},
{"learn":[6194.328876],"iteration":655,"passed_time":26.3420291,"remaining_time":13.81350306},
{"learn":[6192.901391],"iteration":656,"passed_time":26.38668872,"remaining_time":13.77569898},
{"learn":[6191.527029],"iteration":657,"passed_time":26.42976366,"remaining_time":13.73705041},
{"learn":[6190.412498],"iteration":658,"passed_time":26.46958276,"remaining_time":13.69670367},
{"learn":[6188.844191],"iteration":659,"passed_time":26.50672055,"remaining_time":13.65497725},
{"learn":[6185.137029],"iteration":660,"passed_time":26.54253547,"remaining_time":13.61258627},
{"learn":[6182.979317],"iteration":661,"passed_time":26.57975916,"remaining_time":13.57093443},
{"learn":[6181.086586],"iteration":662,"passed_time":26.61516402,"remaining_time":13.52837146},
{"learn":[6179.223028],"iteration":663,"passed_time":26.65276587,"remaining_time":13.48694176},
{"learn":[6175.331017],"iteration":664,"passed_time":26.69489629,"remaining_time":13.4478049},
{"learn":[6173.651985],"iteration":665,"passed_time":26.7359818,"remaining_time":13.40813502},
{"learn":[6171.926821],"iteration":666,"passed_time":26.77887465,"remaining_time":13.36936321},
{"learn":[6170.660066],"iteration":667,"passed_time":26.81953132,"remaining_time":13.32946766},
{"learn":[6168.262096],"iteration":668,"passed_time":26.85518695,"remaining_time":13.28709549},
{"learn":[6167.398023],"iteration":669,"passed_time":26.89115016,"remaining_time":13.24489485},
{"learn":[6164.642698],"iteration":670,"passed_time":26.93128497,"remaining_time":13.20475821},
{"learn":[6162.294817],"iteration":671,"passed_time":26.97222093,"remaining_time":13.16501259},
{"learn":[6160.376917],"iteration":672,"passed_time":27.00658292,"remaining_time":13.12206926},
{"learn":[6158.582001],"iteration":673,"passed_time":27.04459803,"remaining_time":13.08091833},
{"learn":[6157.249874],"iteration":674,"passed_time":27.08089464,"remaining_time":13.03894927},
{"learn":[6155.93972],"iteration":675,"passed_time":27.12262564,"remaining_time":12.99960164},
{"learn":[6148.413329],"iteration":676,"passed_time":27.1636287,"remaining_time":12.95989966},
{"learn":[6145.066586],"iteration":677,"passed_time":27.19954596,"remaining_time":12.91777847},
{"learn":[6136.747891],"iteration":678,"passed_time":27.24053847,"remaining_time":12.87807489},
{"learn":[6132.766436],"iteration":679,"passed_time":27.28446349,"remaining_time":12.83974752},
{"learn":[6131.398333],"iteration":680,"passed_time":27.32190708,"remaining_time":12.79836764},
{"learn":[6127.462426],"iteration":681,"passed_time":27.35963945,"remaining_time":12.75713394},
{"learn":[6125.147002],"iteration":682,"passed_time":27.39470856,"remaining_time":12.7146744},
{"learn":[6118.497854],"iteration":683,"passed_time":27.43511893,"remaining_time":12.67470407},
{"learn":[6115.425756],"iteration":684,"passed_time":27.4712756,"remaining_time":12.63277637},
{"learn":[6113.311184],"iteration":685,"passed_time":27.51114493,"remaining_time":12.59256488},
{"learn":[6109.378715],"iteration":686,"passed_time":27.55106732,"remaining_time":12.55237856},
{"learn":[6107.908606],"iteration":687,"passed_time":27.59178144,"remaining_time":12.51255205},
{"learn":[6105.831448],"iteration":688,"passed_time":27.62950669,"remaining_time":12.47137385},
{"learn":[6103.813297],"iteration":689,"passed_time":27.67093407,"remaining_time":12.43186893},
{"learn":[6100.953268],"iteration":690,"passed_time":27.70673476,"remaining_time":12.38984232},
{"learn":[6100.173422],"iteration":691,"passed_time":27.74543215,"remaining_time":12.34912298},
{"learn":[6098.799042],"iteration":692,"passed_time":27.79411739,"remaining_time":12.31283411},
{"learn":[6096.014605],"iteration":693,"passed_time":27.83128855,"remaining_time":12.2714327},
{"learn":[6092.954025],"iteration":694,"passed_time":27.86698652,"remaining_time":12.22939696},
{"learn":[6091.747559],"iteration":695,"passed_time":27.90571785,"remaining_time":12.18870435},
{"learn":[6088.147455],"iteration":696,"passed_time":27.94593677,"remaining_time":12.14866405},
{"learn":[6086.41295],"iteration":697,"passed_time":27.98369395,"remaining_time":12.10755813},
{"learn":[6084.295326],"iteration":698,"passed_time":28.02741897,"remaining_time":12.06903163},
{"learn":[6083.082793],"iteration":699,"passed_time":28.06708597,"remaining_time":12.02875113},
{"learn":[6081.818688],"iteration":700,"passed_time":28.10464992,"remaining_time":11.98757536},
{"learn":[6080.728661],"iteration":701,"passed_time":28.14250643,"remaining_time":11.94653407},
{"learn":[6073.305905],"iteration":702,"passed_time":28.18136682,"remaining_time":11.90592595},
{"learn":[6071.556447],"iteration":703,"passed_time":28.2174603,"remaining_time":11.86415944},
{"learn":[6067.026791],"iteration":704,"passed_time":28.25928082,"remaining_time":11.82480545},
{"learn":[6065.219948],"iteration":705,"passed_time":28.29747136,"remaining_time":11.78393283},
{"learn":[6063.193284],"iteration":706,"passed_time":28.33706473,"remaining_time":11.74364917},
{"learn":[6061.491713],"iteration":707,"passed_time":28.37647728,"remaining_time":11.70329289},
{"learn":[6059.335231],"iteration":708,"passed_time":28.41350102,"remaining_time":11.66195881},
{"learn":[6057.98813],"iteration":709,"passed_time":28.45472546,"remaining_time":11.62235265},
{"learn":[6056.516716],"iteration":710,"passed_time":28.49441799,"remaining_time":11.58211927},
{"learn":[6055.364638],"iteration":711,"passed_time":28.5288228,"remaining_time":11.53974855},
{"learn":[6052.756456],"iteration":712,"passed_time":28.56595076,"remaining_time":11.49849631},
{"learn":[6051.62663],"iteration":713,"passed_time":28.60639958,"remaining_time":11.45858583},
{"learn":[6050.21569],"iteration":714,"passed_time":28.64555648,"remaining_time":11.41815888},
{"learn":[6048.798917],"iteration":715,"passed_time":28.68644469,"remaining_time":11.37842219},
{"learn":[6044.636257],"iteration":716,"passed_time":28.72846689,"remaining_time":11.33912989},
{"learn":[6042.413299],"iteration":717,"passed_time":28.76872937,"remaining_time":11.29913883},
{"learn":[6041.164994],"iteration":718,"passed_time":28.80423891,"remaining_time":11.25728948},
{"learn":[6039.521801],"iteration":719,"passed_time":28.84179803,"remaining_time":11.21625479},
{"learn":[6038.417286],"iteration":720,"passed_time":28.877699,"remaining_time":11.1745881},
{"learn":[6035.616603],"iteration":721,"passed_time":28.91648949,"remaining_time":11.13404997},
{"learn":[6031.957869],"iteration":722,"passed_time":28.94715075,"remaining_time":11.09040216},
{"learn":[6030.429991],"iteration":723,"passed_time":28.98303182,"remaining_time":11.04878008},
{"learn":[6028.61824],"iteration":724,"passed_time":29.01614321,"remaining_time":11.00612329},
{"learn":[6027.299565],"iteration":725,"passed_time":29.05440845,"remaining_time":10.9654379},
{"learn":[6024.865728],"iteration":726,"passed_time":29.09247646,"remaining_time":10.92468511},
{"learn":[6022.945497],"iteration":727,"passed_time":29.12964393,"remaining_time":10.88360323},
{"learn":[6020.749755],"iteration":728,"passed_time":29.168729,"remaining_time":10.84324494},
{"learn":[6019.243778],"iteration":729,"passed_time":29.20916058,"remaining_time":10.80338816},
{"learn":[6017.837201],"iteration":730,"passed_time":29.24809923,"remaining_time":10.76298043},
{"learn":[6016.799272],"iteration":731,"passed_time":29.28447634,"remaining_time":10.72163888},
{"learn":[6013.819904],"iteration":732,"passed_time":29.32170208,"remaining_time":10.68061999},
{"learn":[6012.350963],"iteration":733,"passed_time":29.35759044,"remaining_time":10.63912678},
{"learn":[6011.211407],"iteration":734,"passed_time":29.39733595,"remaining_time":10.59903949},
{"learn":[6009.167315],"iteration":735,"passed_time":29.44008758,"remaining_time":10.56003141},
{"learn":[6005.911602],"iteration":736,"passed_time":29.47591839,"remaining_time":10.51854347},
{"learn":[6002.854205],"iteration":737,"passed_time":29.51308363,"remaining_time":10.47754459},
{"learn":[6002.364263],"iteration":738,"passed_time":29.54654748,"remaining_time":10.43524884},
{"learn":[5999.692777],"iteration":739,"passed_time":29.58236383,"remaining_time":10.39380351},
{"learn":[5998.395017],"iteration":740,"passed_time":29.62261929,"remaining_time":10.35392496},
{"learn":[5996.609784],"iteration":741,"passed_time":29.66357669,"remaining_time":10.31428947},
{"learn":[5991.85263],"iteration":742,"passed_time":29.69743269,"remaining_time":10.27219408},
{"learn":[5988.671437],"iteration":743,"passed_time":29.735616,"remaining_time":10.23160981},
{"learn":[5986.722105],"iteration":744,"passed_time":29.77334932,"remaining_time":10.19087795},
{"learn":[5985.129296],"iteration":745,"passed_time":29.81351024,"remaining_time":10.1509807},
{"learn":[5984.263971],"iteration":746,"passed_time":29.85330973,"remaining_time":10.11096033},
{"learn":[5982.196209],"iteration":747,"passed_time":29.89353409,"remaining_time":10.07108368},
{"learn":[5979.444941],"iteration":748,"passed_time":29.9302291,"remaining_time":10.03002337},
{"learn":[5978.378777],"iteration":749,"passed_time":29.96671712,"remaining_time":9.988905707},
{"learn":[5972.347678],"iteration":750,"passed_time":30.01057527,"remaining_time":9.950243997},
{"learn":[5969.967292],"iteration":751,"passed_time":30.04834731,"remaining_time":9.909561345},
{"learn":[5968.357108],"iteration":752,"passed_time":30.08890205,"remaining_time":9.869799211},
{"learn":[5966.745117],"iteration":753,"passed_time":30.12791708,"remaining_time":9.829532627},
{"learn":[5965.052932],"iteration":754,"passed_time":30.17038853,"remaining_time":9.790390978},
{"learn":[5963.982257],"iteration":755,"passed_time":30.21302029,"remaining_time":9.751292264},
{"learn":[5961.850533],"iteration":756,"passed_time":30.25484148,"remaining_time":9.711924017},
{"learn":[5960.713099],"iteration":757,"passed_time":30.29563332,"remaining_time":9.672220663},
{"learn":[5959.763581],"iteration":758,"passed_time":30.33467778,"remaining_time":9.631959613},
{"learn":[5958.800313],"iteration":759,"passed_time":30.3710528,"remaining_time":9.590858778},
{"learn":[5956.342535],"iteration":760,"passed_time":30.41209533,"remaining_time":9.551236248},
{"learn":[5955.008652],"iteration":761,"passed_time":30.4487547,"remaining_time":9.51024097},
{"learn":[5952.939397],"iteration":762,"passed_time":30.48910298,"remaining_time":9.470402891},
{"learn":[5950.673489],"iteration":763,"passed_time":30.53028729,"remaining_time":9.430821729},
{"learn":[5948.768998],"iteration":764,"passed_time":30.56767704,"remaining_time":9.390070725},
{"learn":[5945.924866],"iteration":765,"passed_time":30.60439593,"remaining_time":9.349123561},
{"learn":[5935.099186],"iteration":766,"passed_time":30.64055438,"remaining_time":9.308017171},
{"learn":[5933.678296],"iteration":767,"passed_time":30.68149242,"remaining_time":9.268367501},
{"learn":[5930.718286],"iteration":768,"passed_time":30.72232778,"remaining_time":9.228683638},
{"learn":[5929.223417],"iteration":769,"passed_time":30.76395909,"remaining_time":9.189234534},
{"learn":[5924.600504],"iteration":770,"passed_time":30.80633049,"remaining_time":9.149999587},
{"learn":[5921.886995],"iteration":771,"passed_time":30.84634943,"remaining_time":9.110061749},
{"learn":[5920.970415],"iteration":772,"passed_time":30.88331879,"remaining_time":9.069228158},
{"learn":[5920.222201],"iteration":773,"passed_time":30.92471148,"remaining_time":9.029696118},
{"learn":[5918.346524],"iteration":774,"passed_time":30.96900547,"remaining_time":8.991001587},
{"learn":[5915.924566],"iteration":775,"passed_time":31.00821446,"remaining_time":8.950824792},
{"learn":[5913.19044],"iteration":776,"passed_time":31.04881245,"remaining_time":8.911049134},
{"learn":[5912.314335],"iteration":777,"passed_time":31.08320315,"remaining_time":8.869500127},
{"learn":[5910.190378],"iteration":778,"passed_time":31.12727064,"remaining_time":8.830714778},
{"learn":[5907.872415],"iteration":779,"passed_time":31.16844274,"remaining_time":8.791099234},
{"learn":[5905.968948],"iteration":780,"passed_time":31.20785184,"remaining_time":8.750985344},
{"learn":[5903.718002],"iteration":781,"passed_time":31.24804888,"remaining_time":8.711092911},
{"learn":[5903.107306],"iteration":782,"passed_time":31.27878045,"remaining_time":8.668576448},
{"learn":[5901.692114],"iteration":783,"passed_time":31.3196349,"remaining_time":8.628879003},
{"learn":[5899.925271],"iteration":784,"passed_time":31.35764657,"remaining_time":8.588400017},
{"learn":[5896.787344],"iteration":785,"passed_time":31.39850592,"remaining_time":8.54870263},
{"learn":[5894.06096],"iteration":786,"passed_time":31.43755735,"remaining_time":8.508512979},
{"learn":[5892.781517],"iteration":787,"passed_time":31.4774321,"remaining_time":8.468547723},
{"learn":[5890.680985],"iteration":788,"passed_time":31.51552178,"remaining_time":8.428105318},
{"learn":[5889.596772],"iteration":789,"passed_time":31.55237113,"remaining_time":8.387339161},
{"learn":[5888.153505],"iteration":790,"passed_time":31.59082514,"remaining_time":8.347006896},
{"learn":[5884.445333],"iteration":791,"passed_time":31.6268951,"remaining_time":8.306053258},
{"learn":[5882.685187],"iteration":792,"passed_time":31.66492726,"remaining_time":8.265624139},
{"learn":[5881.085893],"iteration":793,"passed_time":31.7046182,"remaining_time":8.225631423},
{"learn":[5877.657601],"iteration":794,"passed_time":31.74794358,"remaining_time":8.186576645},
{"learn":[5875.83663],"iteration":795,"passed_time":31.78260792,"remaining_time":8.145291476},
{"learn":[5874.499143],"iteration":796,"passed_time":31.81828477,"remaining_time":8.104280814},
{"learn":[5873.438098],"iteration":797,"passed_time":31.85977328,"remaining_time":8.064754639},
{"learn":[5870.015599],"iteration":798,"passed_time":31.89681929,"remaining_time":8.024105978},
{"learn":[5867.65904],"iteration":799,"passed_time":31.93467093,"remaining_time":7.983667734},
{"learn":[5862.698995],"iteration":800,"passed_time":31.9758515,"remaining_time":7.944062981},
{"learn":[5860.477744],"iteration":801,"passed_time":32.015804,"remaining_time":7.904151113},
{"learn":[5858.779912],"iteration":802,"passed_time":32.05651126,"remaining_time":7.864424306},
{"learn":[5857.204479],"iteration":803,"passed_time":32.09711894,"remaining_time":7.824670786},
{"learn":[5852.823106],"iteration":804,"passed_time":32.13535899,"remaining_time":7.784341619},
{"learn":[5848.194778],"iteration":805,"passed_time":32.17982972,"remaining_time":7.745517327},
{"learn":[5845.30294],"iteration":806,"passed_time":32.21929857,"remaining_time":7.705482806},
{"learn":[5843.069951],"iteration":807,"passed_time":32.26121561,"remaining_time":7.666031433},
{"learn":[5840.992974],"iteration":808,"passed_time":32.29808392,"remaining_time":7.625381989},
{"learn":[5839.499279],"iteration":809,"passed_time":32.33622794,"remaining_time":7.585041122},
{"learn":[5837.223442],"iteration":810,"passed_time":32.37675511,"remaining_time":7.545261055},
{"learn":[5834.535857],"iteration":811,"passed_time":32.41995498,"remaining_time":7.506097951},
{"learn":[5833.872357],"iteration":812,"passed_time":32.45680301,"remaining_time":7.465463914},
{"learn":[5832.532979],"iteration":813,"passed_time":32.50189953,"remaining_time":7.426723972},
{"learn":[5831.822556],"iteration":814,"passed_time":32.53953746,"remaining_time":7.386275373},
{"learn":[5830.962246],"iteration":815,"passed_time":32.57243661,"remaining_time":7.344765117},
{"learn":[5829.295188],"iteration":816,"passed_time":32.60971489,"remaining_time":7.304256823},
{"learn":[5828.622207],"iteration":817,"passed_time":32.64256093,"remaining_time":7.26277028},
{"learn":[5825.17051],"iteration":818,"passed_time":32.6794712,"remaining_time":7.222203038},
{"learn":[5824.089105],"iteration":819,"passed_time":32.71587545,"remaining_time":7.181533636},
{"learn":[5821.960906],"iteration":820,"passed_time":32.75618537,"remaining_time":7.141726164},
{"learn":[5821.301352],"iteration":821,"passed_time":32.79656092,"remaining_time":7.101931682},
{"learn":[5819.612552],"iteration":822,"passed_time":32.82888748,"remaining_time":7.060404719},
{"learn":[5819.02684],"iteration":823,"passed_time":32.86412389,"remaining_time":7.019521607},
{"learn":[5814.379698],"iteration":824,"passed_time":32.90899467,"remaining_time":6.980695839},
{"learn":[5812.819221],"iteration":825,"passed_time":32.95258676,"remaining_time":6.941586072},
{"learn":[5810.171932],"iteration":826,"passed_time":32.98833436,"remaining_time":6.90082448},
{"learn":[5806.456902],"iteration":827,"passed_time":33.01453874,"remaining_time":6.858092588},
{"learn":[5805.262456],"iteration":828,"passed_time":33.04844984,"remaining_time":6.816990256},
{"learn":[5803.762307],"iteration":829,"passed_time":33.08759598,"remaining_time":6.77697749},
{"learn":[5802.682265],"iteration":830,"passed_time":33.12739402,"remaining_time":6.737099386},
{"learn":[5802.310961],"iteration":831,"passed_time":33.16500585,"remaining_time":6.696780028},
{"learn":[5801.136491],"iteration":832,"passed_time":33.20706905,"remaining_time":6.657359581},
{"learn":[5800.203098],"iteration":833,"passed_time":33.24313554,"remaining_time":6.616739207},
{"learn":[5798.540831],"iteration":834,"passed_time":33.28513452,"remaining_time":6.577302031},
{"learn":[5797.031521],"iteration":835,"passed_time":33.32293921,"remaining_time":6.537035922},
{"learn":[5794.820879],"iteration":836,"passed_time":33.36345136,"remaining_time":6.497302954},
{"learn":[5792.993245],"iteration":837,"passed_time":33.40542755,"remaining_time":6.45785115},
{"learn":[5792.066404],"iteration":838,"passed_time":33.44186244,"remaining_time":6.41732998},
{"learn":[5790.393561],"iteration":839,"passed_time":33.48243821,"remaining_time":6.377607278},
{"learn":[5789.054906],"iteration":840,"passed_time":33.52272214,"remaining_time":6.337827373},
{"learn":[5788.693246],"iteration":841,"passed_time":33.56371887,"remaining_time":6.298180025},
{"learn":[5787.09646],"iteration":842,"passed_time":33.60590708,"remaining_time":6.258751377},
{"learn":[5785.766646],"iteration":843,"passed_time":33.65416056,"remaining_time":6.22043726},
{"learn":[5784.253266],"iteration":844,"passed_time":33.70460988,"remaining_time":6.182502403},
{"learn":[5779.780419],"iteration":845,"passed_time":33.74823677,"remaining_time":6.143296055},
{"learn":[5777.296959],"iteration":846,"passed_time":33.79641091,"remaining_time":6.104900672},
{"learn":[5774.904753],"iteration":847,"passed_time":33.83251126,"remaining_time":6.064318056},
{"learn":[5773.386726],"iteration":848,"passed_time":33.87246851,"remaining_time":6.024431974},
{"learn":[5772.139781],"iteration":849,"passed_time":33.91593429,"remaining_time":5.985164875},
{"learn":[5771.254594],"iteration":850,"passed_time":33.95775804,"remaining_time":5.945600408},
{"learn":[5765.984607],"iteration":851,"passed_time":33.99622813,"remaining_time":5.905448079},
{"learn":[5765.113683],"iteration":852,"passed_time":34.03227342,"remaining_time":5.864881821},
{"learn":[5763.993829],"iteration":853,"passed_time":34.07179257,"remaining_time":5.824920041},
{"learn":[5762.746684],"iteration":854,"passed_time":34.11246724,"remaining_time":5.785155263},
{"learn":[5761.875722],"iteration":855,"passed_time":34.15276332,"remaining_time":5.745324671},
{"learn":[5760.669862],"iteration":856,"passed_time":34.19348175,"remaining_time":5.705563466},
{"learn":[5759.103748],"iteration":857,"passed_time":34.23295259,"remaining_time":5.665593552},
{"learn":[5757.34321],"iteration":858,"passed_time":34.27457002,"remaining_time":5.625977152},
{"learn":[5756.354511],"iteration":859,"passed_time":34.30871172,"remaining_time":5.585139118},
{"learn":[5755.484831],"iteration":860,"passed_time":34.34536173,"remaining_time":5.54472158},
{"learn":[5754.311975],"iteration":861,"passed_time":34.3831617,"remaining_time":5.504496885},
{"learn":[5753.216608],"iteration":862,"passed_time":34.42424069,"remaining_time":5.464798349},
{"learn":[5752.288637],"iteration":863,"passed_time":34.46638355,"remaining_time":5.425264077},
{"learn":[5751.458014],"iteration":864,"passed_time":34.5013978,"remaining_time":5.384611217},
{"learn":[5750.60236],"iteration":865,"passed_time":34.53873487,"remaining_time":5.344330799},
{"learn":[5749.278858],"iteration":866,"passed_time":34.57920185,"remaining_time":5.304537308},
{"learn":[5747.927155],"iteration":867,"passed_time":34.61878184,"remaining_time":5.264607376},
{"learn":[5747.165378],"iteration":868,"passed_time":34.66032585,"remaining_time":5.224974323},
{"learn":[5744.693725],"iteration":869,"passed_time":34.70335729,"remaining_time":5.185559135},
{"learn":[5743.691502],"iteration":870,"passed_time":34.74115862,"remaining_time":5.145361036},
{"learn":[5740.943475],"iteration":871,"passed_time":34.7850146,"remaining_time":5.106057189},
{"learn":[5739.449549],"iteration":872,"passed_time":34.82056175,"remaining_time":5.065534184},
{"learn":[5738.061299],"iteration":873,"passed_time":34.86261871,"remaining_time":5.02596105},
{"learn":[5736.87408],"iteration":874,"passed_time":34.90475454,"remaining_time":4.986393506},
{"learn":[5735.87871],"iteration":875,"passed_time":34.946777,"remaining_time":4.94680405},
{"learn":[5734.927032],"iteration":876,"passed_time":34.98266101,"remaining_time":4.906348123},
{"learn":[5734.609665],"iteration":877,"passed_time":35.01328199,"remaining_time":4.865171302},
{"learn":[5733.872552],"iteration":878,"passed_time":35.0537347,"remaining_time":4.825371899},
{"learn":[5733.010558],"iteration":879,"passed_time":35.09117753,"remaining_time":4.785160573},
{"learn":[5726.341288],"iteration":880,"passed_time":35.12730901,"remaining_time":4.744778402},
{"learn":[5725.874799],"iteration":881,"passed_time":35.16107347,"remaining_time":4.704089194},
{"learn":[5724.584136],"iteration":882,"passed_time":35.19866707,"remaining_time":4.663923043},
{"learn":[5723.002404],"iteration":883,"passed_time":35.24558751,"remaining_time":4.624986596},
{"learn":[5717.251542],"iteration":884,"passed_time":35.28683487,"remaining_time":4.585294926},
{"learn":[5716.454233],"iteration":885,"passed_time":35.32660753,"remaining_time":4.545409998},
{"learn":[5712.975776],"iteration":886,"passed_time":35.36715659,"remaining_time":4.505624233},
{"learn":[5711.349021],"iteration":887,"passed_time":35.40275719,"remaining_time":4.465212618},
{"learn":[5710.156354],"iteration":888,"passed_time":35.44386143,"remaining_time":4.425499008},
{"learn":[5709.251792],"iteration":889,"passed_time":35.46958697,"remaining_time":4.383881535},
{"learn":[5706.111423],"iteration":890,"passed_time":35.50773626,"remaining_time":4.343819587},
{"learn":[5704.858197],"iteration":891,"passed_time":35.54900692,"remaining_time":4.304139851},
{"learn":[5703.8509],"iteration":892,"passed_time":35.59098084,"remaining_time":4.264540818},
{"learn":[5702.870511],"iteration":893,"passed_time":35.6324722,"remaining_time":4.224879255},
{"learn":[5702.184126],"iteration":894,"passed_time":35.66869248,"remaining_time":4.184595207},
{"learn":[5699.826801],"iteration":895,"passed_time":35.70654589,"remaining_time":4.144509791},
{"learn":[5698.058536],"iteration":896,"passed_time":35.74651401,"remaining_time":4.104672177},
{"learn":[5697.549065],"iteration":897,"passed_time":35.78847884,"remaining_time":4.065061071},
{"learn":[5697.013768],"iteration":898,"passed_time":35.82004085,"remaining_time":4.024276002},
{"learn":[5696.163015],"iteration":899,"passed_time":35.86211062,"remaining_time":3.984678958},
{"learn":[5683.807353],"iteration":900,"passed_time":35.90452514,"remaining_time":3.945114305},
{"learn":[5683.276563],"iteration":901,"passed_time":35.94257848,"remaining_time":3.905069503},
{"learn":[5682.587371],"iteration":902,"passed_time":35.98071921,"remaining_time":3.865038497},
{"learn":[5681.278629],"iteration":903,"passed_time":36.02044201,"remaining_time":3.825179683},
{"learn":[5679.210453],"iteration":904,"passed_time":36.06189861,"remaining_time":3.785503169},
{"learn":[5678.442686],"iteration":905,"passed_time":36.10339112,"remaining_time":3.745826451},
{"learn":[5677.216049],"iteration":906,"passed_time":36.1448832,"remaining_time":3.706145686},
{"learn":[5676.544919],"iteration":907,"passed_time":36.18532266,"remaining_time":3.666354278},
{"learn":[5675.487257],"iteration":908,"passed_time":36.2289324,"remaining_time":3.626878821},
{"learn":[5674.233061],"iteration":909,"passed_time":36.27116782,"remaining_time":3.587258356},
{"learn":[5671.048351],"iteration":910,"passed_time":36.31133144,"remaining_time":3.547429745},
{"learn":[5670.128643],"iteration":911,"passed_time":36.35336498,"remaining_time":3.507780832},
{"learn":[5668.589548],"iteration":912,"passed_time":36.39545704,"remaining_time":3.46813227},
{"learn":[5666.712861],"iteration":913,"passed_time":36.43783098,"remaining_time":3.428504885},
{"learn":[5665.440207],"iteration":914,"passed_time":36.47344359,"remaining_time":3.388243393},
{"learn":[5664.409457],"iteration":915,"passed_time":36.50596004,"remaining_time":3.347708126},
{"learn":[5663.704321],"iteration":916,"passed_time":36.54307403,"remaining_time":3.307606483},
{"learn":[5658.041535],"iteration":917,"passed_time":36.57757977,"remaining_time":3.267278368},
{"learn":[5657.002039],"iteration":918,"passed_time":36.61655225,"remaining_time":3.227356618},
{"learn":[5654.190186],"iteration":919,"passed_time":36.65709839,"remaining_time":3.187573773},
{"learn":[5653.597787],"iteration":920,"passed_time":36.69955749,"remaining_time":3.147953357},
{"learn":[5651.599997],"iteration":921,"passed_time":36.73803005,"remaining_time":3.107989527},
{"learn":[5649.7443],"iteration":922,"passed_time":36.77961607,"remaining_time":3.068288665},
{"learn":[5648.631248],"iteration":923,"passed_time":36.81746205,"remaining_time":3.028276099},
{"learn":[5644.799573],"iteration":924,"passed_time":36.86024784,"remaining_time":2.988668744},
{"learn":[5643.764053],"iteration":925,"passed_time":36.89910895,"remaining_time":2.948740888},
{"learn":[5641.358128],"iteration":926,"passed_time":36.94120274,"remaining_time":2.909069903},
{"learn":[5640.740401],"iteration":927,"passed_time":36.98422652,"remaining_time":2.86946585},
{"learn":[5638.543051],"iteration":928,"passed_time":37.0215933,"remaining_time":2.829422093},
{"learn":[5637.401765],"iteration":929,"passed_time":37.05829031,"remaining_time":2.789333679},
{"learn":[5636.682352],"iteration":930,"passed_time":37.09576054,"remaining_time":2.749309857},
{"learn":[5635.011862],"iteration":931,"passed_time":37.13629448,"remaining_time":2.709515048},
{"learn":[5633.739854],"iteration":932,"passed_time":37.17586744,"remaining_time":2.669649645},
{"learn":[5630.243919],"iteration":933,"passed_time":37.21500426,"remaining_time":2.629754049},
{"learn":[5628.78475],"iteration":934,"passed_time":37.25752378,"remaining_time":2.590095236},
{"learn":[5627.261016],"iteration":935,"passed_time":37.30045627,"remaining_time":2.550458548},
{"learn":[5625.712091],"iteration":936,"passed_time":37.34134572,"remaining_time":2.51067746},
{"learn":[5623.779589],"iteration":937,"passed_time":37.37518151,"remaining_time":2.470427776},
{"learn":[5622.966007],"iteration":938,"passed_time":37.4108916,"remaining_time":2.430313512},
{"learn":[5621.50833],"iteration":939,"passed_time":37.45257797,"remaining_time":2.390590083},
{"learn":[5618.701565],"iteration":940,"passed_time":37.4911149,"remaining_time":2.350665015},
{"learn":[5616.964558],"iteration":941,"passed_time":37.53404075,"remaining_time":2.311013125},
{"learn":[5615.529661],"iteration":942,"passed_time":37.57279417,"remaining_time":2.271102087},
{"learn":[5615.117203],"iteration":943,"passed_time":37.61352639,"remaining_time":2.231310888},
{"learn":[5613.474391],"iteration":944,"passed_time":37.65358228,"remaining_time":2.191478334},
{"learn":[5612.628495],"iteration":945,"passed_time":37.69514499,"remaining_time":2.151731321},
{"learn":[5611.428153],"iteration":946,"passed_time":37.72830997,"remaining_time":2.111510484},
{"learn":[5610.476891],"iteration":947,"passed_time":37.76738664,"remaining_time":2.071628803},
{"learn":[5609.078361],"iteration":948,"passed_time":37.80914447,"remaining_time":2.031892906},
{"learn":[5608.043239],"iteration":949,"passed_time":37.84767417,"remaining_time":1.991982851},
{"learn":[5608.032741],"iteration":950,"passed_time":37.87708697,"remaining_time":1.951605953},
{"learn":[5600.639603],"iteration":951,"passed_time":37.91479095,"remaining_time":1.911670132},
{"learn":[5598.39776],"iteration":952,"passed_time":37.95271985,"remaining_time":1.871750087},
{"learn":[5596.120265],"iteration":953,"passed_time":37.99461701,"remaining_time":1.832025558},
{"learn":[5595.299941],"iteration":954,"passed_time":38.0313449,"remaining_time":1.792052901},
{"learn":[5593.729984],"iteration":955,"passed_time":38.07196921,"remaining_time":1.752266365},
{"learn":[5581.546963],"iteration":956,"passed_time":38.11218457,"remaining_time":1.712459704},
{"learn":[5580.308766],"iteration":957,"passed_time":38.14962827,"remaining_time":1.672530676},
{"learn":[5577.252772],"iteration":958,"passed_time":38.19117964,"remaining_time":1.632782446},
{"learn":[5576.499841],"iteration":959,"passed_time":38.23221678,"remaining_time":1.593009033},
{"learn":[5571.588211],"iteration":960,"passed_time":38.27837392,"remaining_time":1.553440773},
{"learn":[5570.945306],"iteration":961,"passed_time":38.3189997,"remaining_time":1.513640321},
{"learn":[5569.665107],"iteration":962,"passed_time":38.35832552,"remaining_time":1.473788208},
{"learn":[5568.760799],"iteration":963,"passed_time":38.39686202,"remaining_time":1.43390771},
{"learn":[5567.878762],"iteration":964,"passed_time":38.43402316,"remaining_time":1.393980115},
{"learn":[5566.521019],"iteration":965,"passed_time":38.47361382,"remaining_time":1.354143757},
{"learn":[5566.163565],"iteration":966,"passed_time":38.51276987,"remaining_time":1.314293077},
{"learn":[5565.223127],"iteration":967,"passed_time":38.55308233,"remaining_time":1.27448206},
{"learn":[5564.978012],"iteration":968,"passed_time":38.58490074,"remaining_time":1.234398269},
{"learn":[5562.491271],"iteration":969,"passed_time":38.62899366,"remaining_time":1.194711144},
{"learn":[5559.107493],"iteration":970,"passed_time":38.67022631,"remaining_time":1.154929519},
{"learn":[5558.170685],"iteration":971,"passed_time":38.71163213,"remaining_time":1.115149897},
{"learn":[5557.461187],"iteration":972,"passed_time":38.7527505,"remaining_time":1.075358955},
{"learn":[5554.773518],"iteration":973,"passed_time":38.79407613,"remaining_time":1.035570821},
{"learn":[5553.18979],"iteration":974,"passed_time":38.83651529,"remaining_time":0.9958080844},
{"learn":[5552.274545],"iteration":975,"passed_time":38.88088923,"remaining_time":0.9560874401},
{"learn":[5550.564661],"iteration":976,"passed_time":38.92348972,"remaining_time":0.9163155206},
{"learn":[5549.104191],"iteration":977,"passed_time":38.96820271,"remaining_time":0.8765853371},
{"learn":[5545.035648],"iteration":978,"passed_time":39.00791836,"remaining_time":0.8367377789},
{"learn":[5543.173861],"iteration":979,"passed_time":39.04834048,"remaining_time":0.7969049078},
{"learn":[5542.273571],"iteration":980,"passed_time":39.09118052,"remaining_time":0.7571176655},
{"learn":[5530.694082],"iteration":981,"passed_time":39.1349812,"remaining_time":0.7173418142},
{"learn":[5529.760822],"iteration":982,"passed_time":39.17585459,"remaining_time":0.6775071495},
{"learn":[5528.870468],"iteration":983,"passed_time":39.21390305,"remaining_time":0.6376244398},
{"learn":[5527.909655],"iteration":984,"passed_time":39.25186283,"remaining_time":0.5977441039},
{"learn":[5526.188968],"iteration":985,"passed_time":39.29150227,"remaining_time":0.557891513},
{"learn":[5523.359041],"iteration":986,"passed_time":39.32969678,"remaining_time":0.5180203224},
{"learn":[5522.442874],"iteration":987,"passed_time":39.37067504,"remaining_time":0.4781863365},
{"learn":[5521.066252],"iteration":988,"passed_time":39.40741589,"remaining_time":0.4383029067},
{"learn":[5520.032286],"iteration":989,"passed_time":39.44488297,"remaining_time":0.3984331613},
{"learn":[5518.775865],"iteration":990,"passed_time":39.48581977,"remaining_time":0.3585997759},
{"learn":[5517.284532],"iteration":991,"passed_time":39.52294817,"remaining_time":0.318733453},
{"learn":[5516.709467],"iteration":992,"passed_time":39.55728484,"remaining_time":0.2788529647},
{"learn":[5515.991815],"iteration":993,"passed_time":39.59726987,"remaining_time":0.2390177256},
{"learn":[5514.692207],"iteration":994,"passed_time":39.64014855,"remaining_time":0.1991967264},
{"learn":[5513.41218],"iteration":995,"passed_time":39.68185676,"remaining_time":0.1593648866},
{"learn":[5512.481969],"iteration":996,"passed_time":39.72542053,"remaining_time":0.1195348662},
{"learn":[5511.477608],"iteration":997,"passed_time":39.76708252,"remaining_time":0.07969355214},
{"learn":[5509.572609],"iteration":998,"passed_time":39.80842525,"remaining_time":0.03984827352},
{"learn":[5509.052414],"iteration":999,"passed_time":39.83999177,"remaining_time":0}
]}